[
{"name": "process_name", "ph": "M", "pid": 0, "args": {"start_time_since_epoch_in_micros":1623318686293364}},
{"name": "process_sort_index", "ph": "M", "pid": 0, "args": {"sort_index": 0}},
{"name": "process_name", "ph": "M", "pid": 1, "args": {"name": "allreduce.noname.1"}},
{"name": "process_sort_index", "ph": "M", "pid": 1, "args": {"sort_index": 1}},
{"ph": "B", "name": "NEGOTIATE_ALLREDUCE", "ts": 3288877, "pid": 1},{"ph": "X", "name": "8", "ts": 3288881, "pid": 1, "dur": 0},{"ph": "X", "name": "9", "ts": 3295442, "pid": 1, "dur": 0},{"ph": "X", "name": "11", "ts": 3342274, "pid": 1, "dur": 0},{"ph": "X", "name": "10", "ts": 3412579, "pid": 1, "dur": 0},{"ph": "X", "name": "13", "ts": 7004557, "pid": 1, "dur": 0},{"ph": "X", "name": "14", "ts": 7044919, "pid": 1, "dur": 0},{"ph": "X", "name": "15", "ts": 7062970, "pid": 1, "dur": 0},{"ph": "X", "name": "12", "ts": 7110889, "pid": 1, "dur": 0},{"ph": "X", "name": "6", "ts": 7215143, "pid": 1, "dur": 0},{"ph": "X", "name": "7", "ts": 7264203, "pid": 1, "dur": 0},{"ph": "X", "name": "5", "ts": 7293973, "pid": 1, "dur": 0},{"ph": "X", "name": "30", "ts": 7317411, "pid": 1, "dur": 0},{"ph": "X", "name": "4", "ts": 7376413, "pid": 1, "dur": 0},{"ph": "X", "name": "28", "ts": 7425726, "pid": 1, "dur": 0},{"ph": "X", "name": "31", "ts": 7440658, "pid": 1, "dur": 0},{"ph": "X", "name": "25", "ts": 7455769, "pid": 1, "dur": 0},{"ph": "X", "name": "29", "ts": 7484735, "pid": 1, "dur": 0},{"ph": "X", "name": "24", "ts": 7501820, "pid": 1, "dur": 0},{"ph": "X", "name": "26", "ts": 7513282, "pid": 1, "dur": 0},{"ph": "X", "name": "27", "ts": 7561787, "pid": 1, "dur": 0},{"ph": "X", "name": "23", "ts": 7562854, "pid": 1, "dur": 0},{"ph": "X", "name": "3", "ts": 7611293, "pid": 1, "dur": 0},{"ph": "X", "name": "19", "ts": 7787487, "pid": 1, "dur": 0},{"ph": "X", "name": "22", "ts": 7817294, "pid": 1, "dur": 0},{"ph": "X", "name": "18", "ts": 7841753, "pid": 1, "dur": 0},{"ph": "X", "name": "0", "ts": 7854452, "pid": 1, "dur": 0},{"ph": "X", "name": "20", "ts": 7864052, "pid": 1, "dur": 0},{"ph": "X", "name": "2", "ts": 7870420, "pid": 1, "dur": 0},{"ph": "X", "name": "21", "ts": 7881071, "pid": 1, "dur": 0},{"ph": "X", "name": "1", "ts": 7929973, "pid": 1, "dur": 0},{"ph": "X", "name": "16", "ts": 7940613, "pid": 1, "dur": 0},{"ph": "X", "name": "17", "ts": 7943797, "pid": 1, "dur": 0},{"ph": "E", "ts": 7943803, "pid": 1},{"ph": "B", "name": "ALLREDUCE", "ts": 7943962, "pid": 1},{"ph": "B", "name": "WAIT_FOR_DATA", "ts": 7943968, "pid": 1},{"ph": "E", "ts": 7943983, "pid": 1},{"ph": "B", "name": "WAIT_FOR_OTHER_TENSOR_DATA", "ts": 7943988, "pid": 1},{"ph": "E", "ts": 7944044, "pid": 1},{"ph": "B", "name": "INIT_NCCL", "ts": 7944083, "pid": 1},{"ph": "E", "ts": 8327390, "pid": 1},{"ph": "B", "name": "QUEUE", "ts": 8331192, "pid": 1},{"ph": "E", "ts": 8331208, "pid": 1},{"ph": "B", "name": "NCCL_ALLREDUCE", "ts": 8331214, "pid": 1},{"ph": "E", "ts": 8334221, "pid": 1},{"ph": "E", "ts": 8334274, "pid": 1, "args": {"dtype": "float32", "shape": "[1]"}},{"name": "process_name", "ph": "M", "pid": 2, "args": {"name": "allreduce.noname.2"}},
{"name": "process_sort_index", "ph": "M", "pid": 2, "args": {"sort_index": 2}},
{"ph": "B", "name": "NEGOTIATE_ALLREDUCE", "ts": 8336454, "pid": 2},{"ph": "X", "name": "0", "ts": 8336456, "pid": 2, "dur": 0},{"ph": "X", "name": "1", "ts": 8336522, "pid": 2, "dur": 0},{"ph": "X", "name": "2", "ts": 8336525, "pid": 2, "dur": 0},{"ph": "X", "name": "16", "ts": 8336535, "pid": 2, "dur": 0},{"ph": "X", "name": "17", "ts": 8336538, "pid": 2, "dur": 0},{"ph": "X", "name": "18", "ts": 8336541, "pid": 2, "dur": 0},{"ph": "X", "name": "19", "ts": 8336543, "pid": 2, "dur": 0},{"ph": "X", "name": "28", "ts": 8336550, "pid": 2, "dur": 0},{"ph": "X", "name": "3", "ts": 8337554, "pid": 2, "dur": 0},{"ph": "X", "name": "4", "ts": 8337556, "pid": 2, "dur": 0},{"ph": "X", "name": "5", "ts": 8337560, "pid": 2, "dur": 0},{"ph": "X", "name": "6", "ts": 8337563, "pid": 2, "dur": 0},{"ph": "X", "name": "7", "ts": 8337566, "pid": 2, "dur": 0},{"ph": "X", "name": "8", "ts": 8337569, "pid": 2, "dur": 0},{"ph": "X", "name": "9", "ts": 8337573, "pid": 2, "dur": 0},{"ph": "X", "name": "10", "ts": 8337576, "pid": 2, "dur": 0},{"ph": "X", "name": "11", "ts": 8337578, "pid": 2, "dur": 0},{"ph": "X", "name": "12", "ts": 8337580, "pid": 2, "dur": 0},{"ph": "X", "name": "15", "ts": 8337584, "pid": 2, "dur": 0},{"ph": "X", "name": "20", "ts": 8337589, "pid": 2, "dur": 0},{"ph": "X", "name": "21", "ts": 8337591, "pid": 2, "dur": 0},{"ph": "X", "name": "23", "ts": 8337593, "pid": 2, "dur": 0},{"ph": "X", "name": "24", "ts": 8337595, "pid": 2, "dur": 0},{"ph": "X", "name": "25", "ts": 8337597, "pid": 2, "dur": 0},{"ph": "X", "name": "26", "ts": 8337599, "pid": 2, "dur": 0},{"ph": "X", "name": "27", "ts": 8337602, "pid": 2, "dur": 0},{"ph": "X", "name": "29", "ts": 8337606, "pid": 2, "dur": 0},{"ph": "X", "name": "30", "ts": 8337608, "pid": 2, "dur": 0},{"ph": "X", "name": "31", "ts": 8337611, "pid": 2, "dur": 0},{"ph": "X", "name": "13", "ts": 8338604, "pid": 2, "dur": 0},{"ph": "X", "name": "14", "ts": 8338607, "pid": 2, "dur": 0},{"ph": "X", "name": "22", "ts": 8338616, "pid": 2, "dur": 0},{"ph": "E", "ts": 8338619, "pid": 2},{"ph": "B", "name": "ALLREDUCE", "ts": 8338681, "pid": 2},{"ph": "B", "name": "WAIT_FOR_DATA", "ts": 8338684, "pid": 2},{"ph": "E", "ts": 8338692, "pid": 2},{"ph": "B", "name": "WAIT_FOR_OTHER_TENSOR_DATA", "ts": 8338695, "pid": 2},{"ph": "E", "ts": 8338754, "pid": 2},{"ph": "B", "name": "QUEUE", "ts": 8338875, "pid": 2},{"ph": "E", "ts": 8338889, "pid": 2},{"ph": "B", "name": "NCCL_ALLREDUCE", "ts": 8338896, "pid": 2},{"ph": "E", "ts": 8338905, "pid": 2},{"ph": "E", "ts": 8338937, "pid": 2, "args": {"dtype": "float32", "shape": "[2]"}},{"name": "process_name", "ph": "M", "pid": 3, "args": {"name": "allreduce.noname.3"}},
{"name": "process_sort_index", "ph": "M", "pid": 3, "args": {"sort_index": 3}},
{"ph": "B", "name": "NEGOTIATE_ALLREDUCE", "ts": 8339689, "pid": 3},{"ph": "X", "name": "28", "ts": 8339692, "pid": 3, "dur": 0},{"ph": "X", "name": "30", "ts": 8339698, "pid": 3, "dur": 0},{"ph": "X", "name": "0", "ts": 8340672, "pid": 3, "dur": 0},{"ph": "X", "name": "1", "ts": 8340746, "pid": 3, "dur": 0},{"ph": "X", "name": "2", "ts": 8340749, "pid": 3, "dur": 0},{"ph": "X", "name": "3", "ts": 8340753, "pid": 3, "dur": 0},{"ph": "X", "name": "4", "ts": 8340757, "pid": 3, "dur": 0},{"ph": "X", "name": "5", "ts": 8340761, "pid": 3, "dur": 0},{"ph": "X", "name": "6", "ts": 8340764, "pid": 3, "dur": 0},{"ph": "X", "name": "7", "ts": 8340768, "pid": 3, "dur": 0},{"ph": "X", "name": "8", "ts": 8340771, "pid": 3, "dur": 0},{"ph": "X", "name": "9", "ts": 8340775, "pid": 3, "dur": 0},{"ph": "X", "name": "10", "ts": 8340778, "pid": 3, "dur": 0},{"ph": "X", "name": "11", "ts": 8340782, "pid": 3, "dur": 0},{"ph": "X", "name": "12", "ts": 8340786, "pid": 3, "dur": 0},{"ph": "X", "name": "13", "ts": 8340790, "pid": 3, "dur": 0},{"ph": "X", "name": "14", "ts": 8340793, "pid": 3, "dur": 0},{"ph": "X", "name": "15", "ts": 8340801, "pid": 3, "dur": 0},{"ph": "X", "name": "16", "ts": 8340805, "pid": 3, "dur": 0},{"ph": "X", "name": "17", "ts": 8340808, "pid": 3, "dur": 0},{"ph": "X", "name": "18", "ts": 8340812, "pid": 3, "dur": 0},{"ph": "X", "name": "19", "ts": 8340815, "pid": 3, "dur": 0},{"ph": "X", "name": "20", "ts": 8340818, "pid": 3, "dur": 0},{"ph": "X", "name": "21", "ts": 8340821, "pid": 3, "dur": 0},{"ph": "X", "name": "22", "ts": 8340825, "pid": 3, "dur": 0},{"ph": "X", "name": "23", "ts": 8340828, "pid": 3, "dur": 0},{"ph": "X", "name": "24", "ts": 8340831, "pid": 3, "dur": 0},{"ph": "X", "name": "25", "ts": 8340835, "pid": 3, "dur": 0},{"ph": "X", "name": "26", "ts": 8340838, "pid": 3, "dur": 0},{"ph": "X", "name": "27", "ts": 8340841, "pid": 3, "dur": 0},{"ph": "X", "name": "29", "ts": 8340845, "pid": 3, "dur": 0},{"ph": "X", "name": "31", "ts": 8340849, "pid": 3, "dur": 0},{"ph": "E", "ts": 8340851, "pid": 3},{"ph": "B", "name": "ALLREDUCE", "ts": 8340895, "pid": 3},{"ph": "B", "name": "WAIT_FOR_DATA", "ts": 8340897, "pid": 3},{"ph": "E", "ts": 8340903, "pid": 3},{"ph": "B", "name": "WAIT_FOR_OTHER_TENSOR_DATA", "ts": 8340906, "pid": 3},{"ph": "E", "ts": 8340964, "pid": 3},{"ph": "B", "name": "QUEUE", "ts": 8341088, "pid": 3},{"ph": "E", "ts": 8341101, "pid": 3},{"ph": "B", "name": "NCCL_ALLREDUCE", "ts": 8341107, "pid": 3},{"ph": "E", "ts": 8341123, "pid": 3},{"ph": "E", "ts": 8341155, "pid": 3, "args": {"dtype": "float32", "shape": "[4]"}},{"name": "process_name", "ph": "M", "pid": 4, "args": {"name": "allreduce.noname.4"}},
{"name": "process_sort_index", "ph": "M", "pid": 4, "args": {"sort_index": 4}},
{"ph": "B", "name": "NEGOTIATE_ALLREDUCE", "ts": 8341797, "pid": 4},{"ph": "X", "name": "28", "ts": 8341800, "pid": 4, "dur": 0},{"ph": "X", "name": "30", "ts": 8341805, "pid": 4, "dur": 0},{"ph": "X", "name": "0", "ts": 8342828, "pid": 4, "dur": 0},{"ph": "X", "name": "1", "ts": 8342876, "pid": 4, "dur": 0},{"ph": "X", "name": "2", "ts": 8342880, "pid": 4, "dur": 0},{"ph": "X", "name": "3", "ts": 8342883, "pid": 4, "dur": 0},{"ph": "X", "name": "4", "ts": 8342887, "pid": 4, "dur": 0},{"ph": "X", "name": "5", "ts": 8342891, "pid": 4, "dur": 0},{"ph": "X", "name": "6", "ts": 8342895, "pid": 4, "dur": 0},{"ph": "X", "name": "7", "ts": 8342898, "pid": 4, "dur": 0},{"ph": "X", "name": "8", "ts": 8342902, "pid": 4, "dur": 0},{"ph": "X", "name": "9", "ts": 8342906, "pid": 4, "dur": 0},{"ph": "X", "name": "10", "ts": 8342910, "pid": 4, "dur": 0},{"ph": "X", "name": "11", "ts": 8342913, "pid": 4, "dur": 0},{"ph": "X", "name": "12", "ts": 8342917, "pid": 4, "dur": 0},{"ph": "X", "name": "13", "ts": 8342921, "pid": 4, "dur": 0},{"ph": "X", "name": "14", "ts": 8342924, "pid": 4, "dur": 0},{"ph": "X", "name": "15", "ts": 8342928, "pid": 4, "dur": 0},{"ph": "X", "name": "16", "ts": 8342931, "pid": 4, "dur": 0},{"ph": "X", "name": "17", "ts": 8342935, "pid": 4, "dur": 0},{"ph": "X", "name": "18", "ts": 8342939, "pid": 4, "dur": 0},{"ph": "X", "name": "19", "ts": 8342942, "pid": 4, "dur": 0},{"ph": "X", "name": "20", "ts": 8342945, "pid": 4, "dur": 0},{"ph": "X", "name": "21", "ts": 8342949, "pid": 4, "dur": 0},{"ph": "X", "name": "22", "ts": 8342952, "pid": 4, "dur": 0},{"ph": "X", "name": "23", "ts": 8342955, "pid": 4, "dur": 0},{"ph": "X", "name": "24", "ts": 8342958, "pid": 4, "dur": 0},{"ph": "X", "name": "25", "ts": 8342962, "pid": 4, "dur": 0},{"ph": "X", "name": "26", "ts": 8342966, "pid": 4, "dur": 0},{"ph": "X", "name": "27", "ts": 8342969, "pid": 4, "dur": 0},{"ph": "X", "name": "29", "ts": 8342973, "pid": 4, "dur": 0},{"ph": "X", "name": "31", "ts": 8342977, "pid": 4, "dur": 0},{"ph": "E", "ts": 8342978, "pid": 4},{"ph": "B", "name": "ALLREDUCE", "ts": 8343019, "pid": 4},{"ph": "B", "name": "WAIT_FOR_DATA", "ts": 8343028, "pid": 4},{"ph": "E", "ts": 8343034, "pid": 4},{"ph": "B", "name": "WAIT_FOR_OTHER_TENSOR_DATA", "ts": 8343037, "pid": 4},{"ph": "E", "ts": 8343097, "pid": 4},{"ph": "B", "name": "QUEUE", "ts": 8343231, "pid": 4},{"ph": "E", "ts": 8343244, "pid": 4},{"ph": "B", "name": "NCCL_ALLREDUCE", "ts": 8343250, "pid": 4},{"ph": "E", "ts": 8343258, "pid": 4},{"ph": "E", "ts": 8343285, "pid": 4, "args": {"dtype": "float32", "shape": "[8]"}},{"name": "process_name", "ph": "M", "pid": 5, "args": {"name": "allreduce.noname.5"}},
{"name": "process_sort_index", "ph": "M", "pid": 5, "args": {"sort_index": 5}},
{"ph": "B", "name": "NEGOTIATE_ALLREDUCE", "ts": 8343928, "pid": 5},{"ph": "X", "name": "28", "ts": 8343930, "pid": 5, "dur": 0},{"ph": "X", "name": "30", "ts": 8343935, "pid": 5, "dur": 0},{"ph": "X", "name": "0", "ts": 8345010, "pid": 5, "dur": 0},{"ph": "X", "name": "1", "ts": 8345046, "pid": 5, "dur": 0},{"ph": "X", "name": "2", "ts": 8345052, "pid": 5, "dur": 0},{"ph": "X", "name": "3", "ts": 8345055, "pid": 5, "dur": 0},{"ph": "X", "name": "4", "ts": 8345059, "pid": 5, "dur": 0},{"ph": "X", "name": "5", "ts": 8345063, "pid": 5, "dur": 0},{"ph": "X", "name": "6", "ts": 8345066, "pid": 5, "dur": 0},{"ph": "X", "name": "7", "ts": 8345070, "pid": 5, "dur": 0},{"ph": "X", "name": "8", "ts": 8345073, "pid": 5, "dur": 0},{"ph": "X", "name": "9", "ts": 8345076, "pid": 5, "dur": 0},{"ph": "X", "name": "10", "ts": 8345080, "pid": 5, "dur": 0},{"ph": "X", "name": "11", "ts": 8345084, "pid": 5, "dur": 0},{"ph": "X", "name": "12", "ts": 8345087, "pid": 5, "dur": 0},{"ph": "X", "name": "13", "ts": 8345091, "pid": 5, "dur": 0},{"ph": "X", "name": "14", "ts": 8345095, "pid": 5, "dur": 0},{"ph": "X", "name": "15", "ts": 8345098, "pid": 5, "dur": 0},{"ph": "X", "name": "16", "ts": 8345102, "pid": 5, "dur": 0},{"ph": "X", "name": "17", "ts": 8345105, "pid": 5, "dur": 0},{"ph": "X", "name": "18", "ts": 8345107, "pid": 5, "dur": 0},{"ph": "X", "name": "19", "ts": 8345111, "pid": 5, "dur": 0},{"ph": "X", "name": "20", "ts": 8345114, "pid": 5, "dur": 0},{"ph": "X", "name": "21", "ts": 8345118, "pid": 5, "dur": 0},{"ph": "X", "name": "22", "ts": 8345121, "pid": 5, "dur": 0},{"ph": "X", "name": "23", "ts": 8345124, "pid": 5, "dur": 0},{"ph": "X", "name": "24", "ts": 8345127, "pid": 5, "dur": 0},{"ph": "X", "name": "25", "ts": 8345130, "pid": 5, "dur": 0},{"ph": "X", "name": "26", "ts": 8345133, "pid": 5, "dur": 0},{"ph": "X", "name": "27", "ts": 8345137, "pid": 5, "dur": 0},{"ph": "X", "name": "29", "ts": 8345141, "pid": 5, "dur": 0},{"ph": "X", "name": "31", "ts": 8345145, "pid": 5, "dur": 0},{"ph": "E", "ts": 8345147, "pid": 5},{"ph": "B", "name": "ALLREDUCE", "ts": 8345191, "pid": 5},{"ph": "B", "name": "WAIT_FOR_DATA", "ts": 8345193, "pid": 5},{"ph": "E", "ts": 8345199, "pid": 5},{"ph": "B", "name": "WAIT_FOR_OTHER_TENSOR_DATA", "ts": 8345203, "pid": 5},{"ph": "E", "ts": 8345263, "pid": 5},{"ph": "B", "name": "QUEUE", "ts": 8345367, "pid": 5},{"ph": "E", "ts": 8345379, "pid": 5},{"ph": "B", "name": "NCCL_ALLREDUCE", "ts": 8345383, "pid": 5},{"ph": "E", "ts": 8345406, "pid": 5},{"ph": "E", "ts": 8345428, "pid": 5, "args": {"dtype": "float32", "shape": "[16]"}},{"name": "process_name", "ph": "M", "pid": 6, "args": {"name": "allreduce.noname.6"}},
{"name": "process_sort_index", "ph": "M", "pid": 6, "args": {"sort_index": 6}},
{"ph": "B", "name": "NEGOTIATE_ALLREDUCE", "ts": 8346090, "pid": 6},{"ph": "X", "name": "28", "ts": 8346093, "pid": 6, "dur": 0},{"ph": "X", "name": "0", "ts": 8347083, "pid": 6, "dur": 0},{"ph": "X", "name": "1", "ts": 8347147, "pid": 6, "dur": 0},{"ph": "X", "name": "2", "ts": 8347151, "pid": 6, "dur": 0},{"ph": "X", "name": "3", "ts": 8347155, "pid": 6, "dur": 0},{"ph": "X", "name": "4", "ts": 8347158, "pid": 6, "dur": 0},{"ph": "X", "name": "5", "ts": 8347163, "pid": 6, "dur": 0},{"ph": "X", "name": "6", "ts": 8347166, "pid": 6, "dur": 0},{"ph": "X", "name": "7", "ts": 8347170, "pid": 6, "dur": 0},{"ph": "X", "name": "8", "ts": 8347174, "pid": 6, "dur": 0},{"ph": "X", "name": "9", "ts": 8347178, "pid": 6, "dur": 0},{"ph": "X", "name": "10", "ts": 8347182, "pid": 6, "dur": 0},{"ph": "X", "name": "11", "ts": 8347185, "pid": 6, "dur": 0},{"ph": "X", "name": "12", "ts": 8347188, "pid": 6, "dur": 0},{"ph": "X", "name": "13", "ts": 8347192, "pid": 6, "dur": 0},{"ph": "X", "name": "14", "ts": 8347195, "pid": 6, "dur": 0},{"ph": "X", "name": "15", "ts": 8347199, "pid": 6, "dur": 0},{"ph": "X", "name": "16", "ts": 8347203, "pid": 6, "dur": 0},{"ph": "X", "name": "17", "ts": 8347206, "pid": 6, "dur": 0},{"ph": "X", "name": "18", "ts": 8347209, "pid": 6, "dur": 0},{"ph": "X", "name": "19", "ts": 8347213, "pid": 6, "dur": 0},{"ph": "X", "name": "20", "ts": 8347216, "pid": 6, "dur": 0},{"ph": "X", "name": "21", "ts": 8347219, "pid": 6, "dur": 0},{"ph": "X", "name": "22", "ts": 8347223, "pid": 6, "dur": 0},{"ph": "X", "name": "23", "ts": 8347226, "pid": 6, "dur": 0},{"ph": "X", "name": "24", "ts": 8347230, "pid": 6, "dur": 0},{"ph": "X", "name": "25", "ts": 8347233, "pid": 6, "dur": 0},{"ph": "X", "name": "26", "ts": 8347236, "pid": 6, "dur": 0},{"ph": "X", "name": "27", "ts": 8347239, "pid": 6, "dur": 0},{"ph": "X", "name": "29", "ts": 8347243, "pid": 6, "dur": 0},{"ph": "X", "name": "30", "ts": 8347248, "pid": 6, "dur": 0},{"ph": "X", "name": "31", "ts": 8347256, "pid": 6, "dur": 0},{"ph": "E", "ts": 8347258, "pid": 6},{"ph": "B", "name": "ALLREDUCE", "ts": 8347299, "pid": 6},{"ph": "B", "name": "WAIT_FOR_DATA", "ts": 8347302, "pid": 6},{"ph": "E", "ts": 8347307, "pid": 6},{"ph": "B", "name": "WAIT_FOR_OTHER_TENSOR_DATA", "ts": 8347310, "pid": 6},{"ph": "E", "ts": 8347368, "pid": 6},{"ph": "B", "name": "QUEUE", "ts": 8347471, "pid": 6},{"ph": "E", "ts": 8347483, "pid": 6},{"ph": "B", "name": "NCCL_ALLREDUCE", "ts": 8347488, "pid": 6},{"ph": "E", "ts": 8347501, "pid": 6},{"ph": "E", "ts": 8347522, "pid": 6, "args": {"dtype": "float32", "shape": "[32]"}},{"name": "process_name", "ph": "M", "pid": 7, "args": {"name": "allreduce.noname.7"}},
{"name": "process_sort_index", "ph": "M", "pid": 7, "args": {"sort_index": 7}},
{"ph": "B", "name": "NEGOTIATE_ALLREDUCE", "ts": 8348213, "pid": 7},{"ph": "X", "name": "28", "ts": 8348215, "pid": 7, "dur": 0},{"ph": "X", "name": "0", "ts": 8349263, "pid": 7, "dur": 0},{"ph": "X", "name": "1", "ts": 8349309, "pid": 7, "dur": 0},{"ph": "X", "name": "2", "ts": 8349312, "pid": 7, "dur": 0},{"ph": "X", "name": "3", "ts": 8349316, "pid": 7, "dur": 0},{"ph": "X", "name": "4", "ts": 8349319, "pid": 7, "dur": 0},{"ph": "X", "name": "5", "ts": 8349322, "pid": 7, "dur": 0},{"ph": "X", "name": "6", "ts": 8349326, "pid": 7, "dur": 0},{"ph": "X", "name": "7", "ts": 8349329, "pid": 7, "dur": 0},{"ph": "X", "name": "8", "ts": 8349334, "pid": 7, "dur": 0},{"ph": "X", "name": "9", "ts": 8349338, "pid": 7, "dur": 0},{"ph": "X", "name": "10", "ts": 8349341, "pid": 7, "dur": 0},{"ph": "X", "name": "11", "ts": 8349344, "pid": 7, "dur": 0},{"ph": "X", "name": "12", "ts": 8349347, "pid": 7, "dur": 0},{"ph": "X", "name": "13", "ts": 8349350, "pid": 7, "dur": 0},{"ph": "X", "name": "14", "ts": 8349353, "pid": 7, "dur": 0},{"ph": "X", "name": "15", "ts": 8349357, "pid": 7, "dur": 0},{"ph": "X", "name": "16", "ts": 8349360, "pid": 7, "dur": 0},{"ph": "X", "name": "17", "ts": 8349363, "pid": 7, "dur": 0},{"ph": "X", "name": "18", "ts": 8349366, "pid": 7, "dur": 0},{"ph": "X", "name": "19", "ts": 8349370, "pid": 7, "dur": 0},{"ph": "X", "name": "20", "ts": 8349373, "pid": 7, "dur": 0},{"ph": "X", "name": "21", "ts": 8349377, "pid": 7, "dur": 0},{"ph": "X", "name": "22", "ts": 8349380, "pid": 7, "dur": 0},{"ph": "X", "name": "23", "ts": 8349383, "pid": 7, "dur": 0},{"ph": "X", "name": "24", "ts": 8349387, "pid": 7, "dur": 0},{"ph": "X", "name": "25", "ts": 8349390, "pid": 7, "dur": 0},{"ph": "X", "name": "26", "ts": 8349393, "pid": 7, "dur": 0},{"ph": "X", "name": "27", "ts": 8349396, "pid": 7, "dur": 0},{"ph": "X", "name": "29", "ts": 8349400, "pid": 7, "dur": 0},{"ph": "X", "name": "30", "ts": 8349404, "pid": 7, "dur": 0},{"ph": "X", "name": "31", "ts": 8349407, "pid": 7, "dur": 0},{"ph": "E", "ts": 8349409, "pid": 7},{"ph": "B", "name": "ALLREDUCE", "ts": 8349449, "pid": 7},{"ph": "B", "name": "WAIT_FOR_DATA", "ts": 8349451, "pid": 7},{"ph": "E", "ts": 8349456, "pid": 7},{"ph": "B", "name": "WAIT_FOR_OTHER_TENSOR_DATA", "ts": 8349460, "pid": 7},{"ph": "E", "ts": 8349519, "pid": 7},{"ph": "B", "name": "QUEUE", "ts": 8349627, "pid": 7},{"ph": "E", "ts": 8349639, "pid": 7},{"ph": "B", "name": "NCCL_ALLREDUCE", "ts": 8349643, "pid": 7},{"ph": "E", "ts": 8349652, "pid": 7},{"ph": "E", "ts": 8349674, "pid": 7, "args": {"dtype": "float32", "shape": "[64]"}},{"name": "process_name", "ph": "M", "pid": 8, "args": {"name": "allreduce.noname.8"}},
{"name": "process_sort_index", "ph": "M", "pid": 8, "args": {"sort_index": 8}},
{"ph": "B", "name": "NEGOTIATE_ALLREDUCE", "ts": 8350369, "pid": 8},{"ph": "X", "name": "28", "ts": 8350371, "pid": 8, "dur": 0},{"ph": "X", "name": "0", "ts": 8351375, "pid": 8, "dur": 0},{"ph": "X", "name": "1", "ts": 8351430, "pid": 8, "dur": 0},{"ph": "X", "name": "2", "ts": 8351433, "pid": 8, "dur": 0},{"ph": "X", "name": "3", "ts": 8351437, "pid": 8, "dur": 0},{"ph": "X", "name": "4", "ts": 8351441, "pid": 8, "dur": 0},{"ph": "X", "name": "5", "ts": 8351443, "pid": 8, "dur": 0},{"ph": "X", "name": "6", "ts": 8351447, "pid": 8, "dur": 0},{"ph": "X", "name": "7", "ts": 8351450, "pid": 8, "dur": 0},{"ph": "X", "name": "8", "ts": 8351453, "pid": 8, "dur": 0},{"ph": "X", "name": "9", "ts": 8351456, "pid": 8, "dur": 0},{"ph": "X", "name": "10", "ts": 8351460, "pid": 8, "dur": 0},{"ph": "X", "name": "11", "ts": 8351463, "pid": 8, "dur": 0},{"ph": "X", "name": "12", "ts": 8351466, "pid": 8, "dur": 0},{"ph": "X", "name": "13", "ts": 8351470, "pid": 8, "dur": 0},{"ph": "X", "name": "14", "ts": 8351473, "pid": 8, "dur": 0},{"ph": "X", "name": "15", "ts": 8351480, "pid": 8, "dur": 0},{"ph": "X", "name": "16", "ts": 8351483, "pid": 8, "dur": 0},{"ph": "X", "name": "17", "ts": 8351486, "pid": 8, "dur": 0},{"ph": "X", "name": "18", "ts": 8351489, "pid": 8, "dur": 0},{"ph": "X", "name": "19", "ts": 8351493, "pid": 8, "dur": 0},{"ph": "X", "name": "20", "ts": 8351496, "pid": 8, "dur": 0},{"ph": "X", "name": "21", "ts": 8351499, "pid": 8, "dur": 0},{"ph": "X", "name": "22", "ts": 8351503, "pid": 8, "dur": 0},{"ph": "X", "name": "23", "ts": 8351506, "pid": 8, "dur": 0},{"ph": "X", "name": "24", "ts": 8351509, "pid": 8, "dur": 0},{"ph": "X", "name": "25", "ts": 8351511, "pid": 8, "dur": 0},{"ph": "X", "name": "26", "ts": 8351515, "pid": 8, "dur": 0},{"ph": "X", "name": "27", "ts": 8351518, "pid": 8, "dur": 0},{"ph": "X", "name": "29", "ts": 8351522, "pid": 8, "dur": 0},{"ph": "X", "name": "30", "ts": 8351525, "pid": 8, "dur": 0},{"ph": "X", "name": "31", "ts": 8351528, "pid": 8, "dur": 0},{"ph": "E", "ts": 8351531, "pid": 8},{"ph": "B", "name": "ALLREDUCE", "ts": 8351571, "pid": 8},{"ph": "B", "name": "WAIT_FOR_DATA", "ts": 8351573, "pid": 8},{"ph": "E", "ts": 8351578, "pid": 8},{"ph": "B", "name": "WAIT_FOR_OTHER_TENSOR_DATA", "ts": 8351581, "pid": 8},{"ph": "E", "ts": 8351640, "pid": 8},{"ph": "B", "name": "QUEUE", "ts": 8351742, "pid": 8},{"ph": "E", "ts": 8351754, "pid": 8},{"ph": "B", "name": "NCCL_ALLREDUCE", "ts": 8351758, "pid": 8},{"ph": "E", "ts": 8351768, "pid": 8},{"ph": "E", "ts": 8351790, "pid": 8, "args": {"dtype": "float32", "shape": "[128]"}},{"name": "process_name", "ph": "M", "pid": 9, "args": {"name": "allreduce.noname.9"}},
{"name": "process_sort_index", "ph": "M", "pid": 9, "args": {"sort_index": 9}},
{"ph": "B", "name": "NEGOTIATE_ALLREDUCE", "ts": 8352497, "pid": 9},{"ph": "X", "name": "28", "ts": 8352499, "pid": 9, "dur": 0},{"ph": "X", "name": "0", "ts": 8353590, "pid": 9, "dur": 0},{"ph": "X", "name": "1", "ts": 8353624, "pid": 9, "dur": 0},{"ph": "X", "name": "2", "ts": 8353628, "pid": 9, "dur": 0},{"ph": "X", "name": "3", "ts": 8353631, "pid": 9, "dur": 0},{"ph": "X", "name": "4", "ts": 8353634, "pid": 9, "dur": 0},{"ph": "X", "name": "5", "ts": 8353638, "pid": 9, "dur": 0},{"ph": "X", "name": "6", "ts": 8353641, "pid": 9, "dur": 0},{"ph": "X", "name": "7", "ts": 8353645, "pid": 9, "dur": 0},{"ph": "X", "name": "8", "ts": 8353648, "pid": 9, "dur": 0},{"ph": "X", "name": "9", "ts": 8353652, "pid": 9, "dur": 0},{"ph": "X", "name": "10", "ts": 8353656, "pid": 9, "dur": 0},{"ph": "X", "name": "11", "ts": 8353659, "pid": 9, "dur": 0},{"ph": "X", "name": "12", "ts": 8353662, "pid": 9, "dur": 0},{"ph": "X", "name": "13", "ts": 8353666, "pid": 9, "dur": 0},{"ph": "X", "name": "14", "ts": 8353669, "pid": 9, "dur": 0},{"ph": "X", "name": "15", "ts": 8353672, "pid": 9, "dur": 0},{"ph": "X", "name": "16", "ts": 8353675, "pid": 9, "dur": 0},{"ph": "X", "name": "17", "ts": 8353679, "pid": 9, "dur": 0},{"ph": "X", "name": "18", "ts": 8353682, "pid": 9, "dur": 0},{"ph": "X", "name": "19", "ts": 8353687, "pid": 9, "dur": 0},{"ph": "X", "name": "20", "ts": 8353690, "pid": 9, "dur": 0},{"ph": "X", "name": "21", "ts": 8353695, "pid": 9, "dur": 0},{"ph": "X", "name": "22", "ts": 8353698, "pid": 9, "dur": 0},{"ph": "X", "name": "23", "ts": 8353701, "pid": 9, "dur": 0},{"ph": "X", "name": "24", "ts": 8353705, "pid": 9, "dur": 0},{"ph": "X", "name": "25", "ts": 8353708, "pid": 9, "dur": 0},{"ph": "X", "name": "26", "ts": 8353711, "pid": 9, "dur": 0},{"ph": "X", "name": "27", "ts": 8353714, "pid": 9, "dur": 0},{"ph": "X", "name": "29", "ts": 8353718, "pid": 9, "dur": 0},{"ph": "X", "name": "30", "ts": 8353721, "pid": 9, "dur": 0},{"ph": "X", "name": "31", "ts": 8353724, "pid": 9, "dur": 0},{"ph": "E", "ts": 8353727, "pid": 9},{"ph": "B", "name": "ALLREDUCE", "ts": 8353766, "pid": 9},{"ph": "B", "name": "WAIT_FOR_DATA", "ts": 8353769, "pid": 9},{"ph": "E", "ts": 8353773, "pid": 9},{"ph": "B", "name": "WAIT_FOR_OTHER_TENSOR_DATA", "ts": 8353775, "pid": 9},{"ph": "E", "ts": 8353832, "pid": 9},{"ph": "B", "name": "QUEUE", "ts": 8353963, "pid": 9},{"ph": "E", "ts": 8353974, "pid": 9},{"ph": "B", "name": "NCCL_ALLREDUCE", "ts": 8353978, "pid": 9},{"ph": "E", "ts": 8353995, "pid": 9},{"ph": "E", "ts": 8354016, "pid": 9, "args": {"dtype": "float32", "shape": "[256]"}},{"name": "process_name", "ph": "M", "pid": 10, "args": {"name": "allreduce.noname.10"}},
{"name": "process_sort_index", "ph": "M", "pid": 10, "args": {"sort_index": 10}},
{"ph": "B", "name": "NEGOTIATE_ALLREDUCE", "ts": 8354671, "pid": 10},{"ph": "X", "name": "28", "ts": 8354673, "pid": 10, "dur": 0},{"ph": "X", "name": "0", "ts": 8355752, "pid": 10, "dur": 0},{"ph": "X", "name": "1", "ts": 8355789, "pid": 10, "dur": 0},{"ph": "X", "name": "2", "ts": 8355793, "pid": 10, "dur": 0},{"ph": "X", "name": "3", "ts": 8355795, "pid": 10, "dur": 0},{"ph": "X", "name": "4", "ts": 8355799, "pid": 10, "dur": 0},{"ph": "X", "name": "5", "ts": 8355801, "pid": 10, "dur": 0},{"ph": "X", "name": "6", "ts": 8355805, "pid": 10, "dur": 0},{"ph": "X", "name": "7", "ts": 8355808, "pid": 10, "dur": 0},{"ph": "X", "name": "8", "ts": 8355811, "pid": 10, "dur": 0},{"ph": "X", "name": "9", "ts": 8355815, "pid": 10, "dur": 0},{"ph": "X", "name": "10", "ts": 8355819, "pid": 10, "dur": 0},{"ph": "X", "name": "11", "ts": 8355822, "pid": 10, "dur": 0},{"ph": "X", "name": "12", "ts": 8355826, "pid": 10, "dur": 0},{"ph": "X", "name": "13", "ts": 8355830, "pid": 10, "dur": 0},{"ph": "X", "name": "14", "ts": 8355833, "pid": 10, "dur": 0},{"ph": "X", "name": "15", "ts": 8355837, "pid": 10, "dur": 0},{"ph": "X", "name": "16", "ts": 8355841, "pid": 10, "dur": 0},{"ph": "X", "name": "17", "ts": 8355845, "pid": 10, "dur": 0},{"ph": "X", "name": "18", "ts": 8355847, "pid": 10, "dur": 0},{"ph": "X", "name": "19", "ts": 8355851, "pid": 10, "dur": 0},{"ph": "X", "name": "20", "ts": 8355854, "pid": 10, "dur": 0},{"ph": "X", "name": "21", "ts": 8355857, "pid": 10, "dur": 0},{"ph": "X", "name": "22", "ts": 8355860, "pid": 10, "dur": 0},{"ph": "X", "name": "23", "ts": 8355864, "pid": 10, "dur": 0},{"ph": "X", "name": "24", "ts": 8355867, "pid": 10, "dur": 0},{"ph": "X", "name": "25", "ts": 8355871, "pid": 10, "dur": 0},{"ph": "X", "name": "26", "ts": 8355875, "pid": 10, "dur": 0},{"ph": "X", "name": "27", "ts": 8355878, "pid": 10, "dur": 0},{"ph": "X", "name": "29", "ts": 8355882, "pid": 10, "dur": 0},{"ph": "X", "name": "30", "ts": 8355885, "pid": 10, "dur": 0},{"ph": "X", "name": "31", "ts": 8355889, "pid": 10, "dur": 0},{"ph": "E", "ts": 8355891, "pid": 10},{"ph": "B", "name": "ALLREDUCE", "ts": 8355933, "pid": 10},{"ph": "B", "name": "WAIT_FOR_DATA", "ts": 8355936, "pid": 10},{"ph": "E", "ts": 8355941, "pid": 10},{"ph": "B", "name": "WAIT_FOR_OTHER_TENSOR_DATA", "ts": 8355944, "pid": 10},{"ph": "E", "ts": 8356001, "pid": 10},{"ph": "B", "name": "QUEUE", "ts": 8356115, "pid": 10},{"ph": "E", "ts": 8356127, "pid": 10},{"ph": "B", "name": "NCCL_ALLREDUCE", "ts": 8356132, "pid": 10},{"ph": "E", "ts": 8356163, "pid": 10},{"ph": "E", "ts": 8356190, "pid": 10, "args": {"dtype": "float32", "shape": "[512]"}},{"name": "process_name", "ph": "M", "pid": 11, "args": {"name": "allreduce.noname.11"}},
{"name": "process_sort_index", "ph": "M", "pid": 11, "args": {"sort_index": 11}},
{"ph": "B", "name": "NEGOTIATE_ALLREDUCE", "ts": 8356838, "pid": 11},{"ph": "X", "name": "28", "ts": 8356840, "pid": 11, "dur": 0},{"ph": "X", "name": "0", "ts": 8357920, "pid": 11, "dur": 0},{"ph": "X", "name": "1", "ts": 8357954, "pid": 11, "dur": 0},{"ph": "X", "name": "2", "ts": 8357957, "pid": 11, "dur": 0},{"ph": "X", "name": "3", "ts": 8357961, "pid": 11, "dur": 0},{"ph": "X", "name": "4", "ts": 8357965, "pid": 11, "dur": 0},{"ph": "X", "name": "5", "ts": 8357969, "pid": 11, "dur": 0},{"ph": "X", "name": "6", "ts": 8357972, "pid": 11, "dur": 0},{"ph": "X", "name": "7", "ts": 8357976, "pid": 11, "dur": 0},{"ph": "X", "name": "8", "ts": 8357980, "pid": 11, "dur": 0},{"ph": "X", "name": "9", "ts": 8357984, "pid": 11, "dur": 0},{"ph": "X", "name": "10", "ts": 8357987, "pid": 11, "dur": 0},{"ph": "X", "name": "11", "ts": 8357991, "pid": 11, "dur": 0},{"ph": "X", "name": "12", "ts": 8357994, "pid": 11, "dur": 0},{"ph": "X", "name": "13", "ts": 8357996, "pid": 11, "dur": 0},{"ph": "X", "name": "14", "ts": 8358000, "pid": 11, "dur": 0},{"ph": "X", "name": "15", "ts": 8358003, "pid": 11, "dur": 0},{"ph": "X", "name": "16", "ts": 8358006, "pid": 11, "dur": 0},{"ph": "X", "name": "17", "ts": 8358010, "pid": 11, "dur": 0},{"ph": "X", "name": "18", "ts": 8358013, "pid": 11, "dur": 0},{"ph": "X", "name": "19", "ts": 8358017, "pid": 11, "dur": 0},{"ph": "X", "name": "20", "ts": 8358021, "pid": 11, "dur": 0},{"ph": "X", "name": "21", "ts": 8358024, "pid": 11, "dur": 0},{"ph": "X", "name": "22", "ts": 8358027, "pid": 11, "dur": 0},{"ph": "X", "name": "23", "ts": 8358029, "pid": 11, "dur": 0},{"ph": "X", "name": "24", "ts": 8358032, "pid": 11, "dur": 0},{"ph": "X", "name": "25", "ts": 8358035, "pid": 11, "dur": 0},{"ph": "X", "name": "26", "ts": 8358038, "pid": 11, "dur": 0},{"ph": "X", "name": "27", "ts": 8358042, "pid": 11, "dur": 0},{"ph": "X", "name": "29", "ts": 8358046, "pid": 11, "dur": 0},{"ph": "X", "name": "30", "ts": 8358053, "pid": 11, "dur": 0},{"ph": "X", "name": "31", "ts": 8358057, "pid": 11, "dur": 0},{"ph": "E", "ts": 8358058, "pid": 11},{"ph": "B", "name": "ALLREDUCE", "ts": 8358098, "pid": 11},{"ph": "B", "name": "WAIT_FOR_DATA", "ts": 8358100, "pid": 11},{"ph": "E", "ts": 8358105, "pid": 11},{"ph": "B", "name": "WAIT_FOR_OTHER_TENSOR_DATA", "ts": 8358107, "pid": 11},{"ph": "E", "ts": 8358174, "pid": 11},{"ph": "B", "name": "QUEUE", "ts": 8358236, "pid": 11},{"ph": "E", "ts": 8358248, "pid": 11},{"ph": "B", "name": "NCCL_ALLREDUCE", "ts": 8358254, "pid": 11},{"ph": "E", "ts": 8358303, "pid": 11},{"ph": "E", "ts": 8358329, "pid": 11, "args": {"dtype": "float32", "shape": "[1024]"}},{"name": "process_name", "ph": "M", "pid": 12, "args": {"name": "allreduce.noname.12"}},
{"name": "process_sort_index", "ph": "M", "pid": 12, "args": {"sort_index": 12}},
{"ph": "B", "name": "NEGOTIATE_ALLREDUCE", "ts": 8358998, "pid": 12},{"ph": "X", "name": "28", "ts": 8359000, "pid": 12, "dur": 0},{"ph": "X", "name": "0", "ts": 8360060, "pid": 12, "dur": 0},{"ph": "X", "name": "1", "ts": 8360104, "pid": 12, "dur": 0},{"ph": "X", "name": "2", "ts": 8360108, "pid": 12, "dur": 0},{"ph": "X", "name": "3", "ts": 8360111, "pid": 12, "dur": 0},{"ph": "X", "name": "4", "ts": 8360114, "pid": 12, "dur": 0},{"ph": "X", "name": "5", "ts": 8360118, "pid": 12, "dur": 0},{"ph": "X", "name": "6", "ts": 8360121, "pid": 12, "dur": 0},{"ph": "X", "name": "7", "ts": 8360124, "pid": 12, "dur": 0},{"ph": "X", "name": "8", "ts": 8360128, "pid": 12, "dur": 0},{"ph": "X", "name": "9", "ts": 8360131, "pid": 12, "dur": 0},{"ph": "X", "name": "10", "ts": 8360135, "pid": 12, "dur": 0},{"ph": "X", "name": "11", "ts": 8360138, "pid": 12, "dur": 0},{"ph": "X", "name": "12", "ts": 8360141, "pid": 12, "dur": 0},{"ph": "X", "name": "13", "ts": 8360144, "pid": 12, "dur": 0},{"ph": "X", "name": "14", "ts": 8360148, "pid": 12, "dur": 0},{"ph": "X", "name": "15", "ts": 8360151, "pid": 12, "dur": 0},{"ph": "X", "name": "16", "ts": 8360154, "pid": 12, "dur": 0},{"ph": "X", "name": "17", "ts": 8360157, "pid": 12, "dur": 0},{"ph": "X", "name": "18", "ts": 8360160, "pid": 12, "dur": 0},{"ph": "X", "name": "19", "ts": 8360165, "pid": 12, "dur": 0},{"ph": "X", "name": "20", "ts": 8360169, "pid": 12, "dur": 0},{"ph": "X", "name": "21", "ts": 8360172, "pid": 12, "dur": 0},{"ph": "X", "name": "22", "ts": 8360175, "pid": 12, "dur": 0},{"ph": "X", "name": "23", "ts": 8360179, "pid": 12, "dur": 0},{"ph": "X", "name": "24", "ts": 8360182, "pid": 12, "dur": 0},{"ph": "X", "name": "25", "ts": 8360185, "pid": 12, "dur": 0},{"ph": "X", "name": "26", "ts": 8360188, "pid": 12, "dur": 0},{"ph": "X", "name": "27", "ts": 8360191, "pid": 12, "dur": 0},{"ph": "X", "name": "29", "ts": 8360195, "pid": 12, "dur": 0},{"ph": "X", "name": "30", "ts": 8360198, "pid": 12, "dur": 0},{"ph": "X", "name": "31", "ts": 8360201, "pid": 12, "dur": 0},{"ph": "E", "ts": 8360204, "pid": 12},{"ph": "B", "name": "ALLREDUCE", "ts": 8360247, "pid": 12},{"ph": "B", "name": "WAIT_FOR_DATA", "ts": 8360250, "pid": 12},{"ph": "E", "ts": 8360254, "pid": 12},{"ph": "B", "name": "WAIT_FOR_OTHER_TENSOR_DATA", "ts": 8360257, "pid": 12},{"ph": "E", "ts": 8360316, "pid": 12},{"ph": "B", "name": "QUEUE", "ts": 8360429, "pid": 12},{"ph": "E", "ts": 8360440, "pid": 12},{"ph": "B", "name": "NCCL_ALLREDUCE", "ts": 8360446, "pid": 12},{"ph": "E", "ts": 8362614, "pid": 12},{"ph": "E", "ts": 8362640, "pid": 12, "args": {"dtype": "float32", "shape": "[2048]"}},{"name": "process_name", "ph": "M", "pid": 13, "args": {"name": "allreduce.noname.13"}},
{"name": "process_sort_index", "ph": "M", "pid": 13, "args": {"sort_index": 13}},
{"ph": "B", "name": "NEGOTIATE_ALLREDUCE", "ts": 8363282, "pid": 13},{"ph": "X", "name": "4", "ts": 8363284, "pid": 13, "dur": 0},{"ph": "X", "name": "5", "ts": 8363290, "pid": 13, "dur": 0},{"ph": "X", "name": "6", "ts": 8363293, "pid": 13, "dur": 0},{"ph": "X", "name": "7", "ts": 8363298, "pid": 13, "dur": 0},{"ph": "X", "name": "12", "ts": 8363304, "pid": 13, "dur": 0},{"ph": "X", "name": "13", "ts": 8363308, "pid": 13, "dur": 0},{"ph": "X", "name": "14", "ts": 8363311, "pid": 13, "dur": 0},{"ph": "X", "name": "15", "ts": 8363314, "pid": 13, "dur": 0},{"ph": "X", "name": "20", "ts": 8363321, "pid": 13, "dur": 0},{"ph": "X", "name": "21", "ts": 8363325, "pid": 13, "dur": 0},{"ph": "X", "name": "22", "ts": 8363329, "pid": 13, "dur": 0},{"ph": "X", "name": "23", "ts": 8363332, "pid": 13, "dur": 0},{"ph": "X", "name": "28", "ts": 8363339, "pid": 13, "dur": 0},{"ph": "X", "name": "29", "ts": 8363343, "pid": 13, "dur": 0},{"ph": "X", "name": "30", "ts": 8363346, "pid": 13, "dur": 0},{"ph": "X", "name": "31", "ts": 8363350, "pid": 13, "dur": 0},{"ph": "X", "name": "0", "ts": 8364377, "pid": 13, "dur": 0},{"ph": "X", "name": "1", "ts": 8364408, "pid": 13, "dur": 0},{"ph": "X", "name": "2", "ts": 8364412, "pid": 13, "dur": 0},{"ph": "X", "name": "3", "ts": 8364415, "pid": 13, "dur": 0},{"ph": "X", "name": "8", "ts": 8364421, "pid": 13, "dur": 0},{"ph": "X", "name": "9", "ts": 8364424, "pid": 13, "dur": 0},{"ph": "X", "name": "10", "ts": 8364428, "pid": 13, "dur": 0},{"ph": "X", "name": "11", "ts": 8364432, "pid": 13, "dur": 0},{"ph": "X", "name": "16", "ts": 8364438, "pid": 13, "dur": 0},{"ph": "X", "name": "17", "ts": 8364442, "pid": 13, "dur": 0},{"ph": "X", "name": "18", "ts": 8364446, "pid": 13, "dur": 0},{"ph": "X", "name": "19", "ts": 8364449, "pid": 13, "dur": 0},{"ph": "X", "name": "24", "ts": 8364455, "pid": 13, "dur": 0},{"ph": "X", "name": "25", "ts": 8364459, "pid": 13, "dur": 0},{"ph": "X", "name": "26", "ts": 8364462, "pid": 13, "dur": 0},{"ph": "X", "name": "27", "ts": 8364465, "pid": 13, "dur": 0},{"ph": "E", "ts": 8364467, "pid": 13},{"ph": "B", "name": "ALLREDUCE", "ts": 8364508, "pid": 13},{"ph": "B", "name": "WAIT_FOR_DATA", "ts": 8364511, "pid": 13},{"ph": "E", "ts": 8364516, "pid": 13},{"ph": "B", "name": "WAIT_FOR_OTHER_TENSOR_DATA", "ts": 8364520, "pid": 13},{"ph": "E", "ts": 8364579, "pid": 13},{"ph": "B", "name": "QUEUE", "ts": 8364705, "pid": 13},{"ph": "E", "ts": 8364718, "pid": 13},{"ph": "B", "name": "NCCL_ALLREDUCE", "ts": 8364726, "pid": 13},{"ph": "E", "ts": 8364860, "pid": 13},{"ph": "E", "ts": 8364887, "pid": 13, "args": {"dtype": "float32", "shape": "[4096]"}},{"name": "process_name", "ph": "M", "pid": 14, "args": {"name": "allreduce.noname.14"}},
{"name": "process_sort_index", "ph": "M", "pid": 14, "args": {"sort_index": 14}},
{"ph": "B", "name": "NEGOTIATE_ALLREDUCE", "ts": 8365468, "pid": 14},{"ph": "X", "name": "28", "ts": 8365470, "pid": 14, "dur": 0},{"ph": "X", "name": "0", "ts": 8366547, "pid": 14, "dur": 0},{"ph": "X", "name": "1", "ts": 8366600, "pid": 14, "dur": 0},{"ph": "X", "name": "2", "ts": 8366604, "pid": 14, "dur": 0},{"ph": "X", "name": "3", "ts": 8366607, "pid": 14, "dur": 0},{"ph": "X", "name": "4", "ts": 8366610, "pid": 14, "dur": 0},{"ph": "X", "name": "5", "ts": 8366613, "pid": 14, "dur": 0},{"ph": "X", "name": "6", "ts": 8366617, "pid": 14, "dur": 0},{"ph": "X", "name": "7", "ts": 8366619, "pid": 14, "dur": 0},{"ph": "X", "name": "8", "ts": 8366622, "pid": 14, "dur": 0},{"ph": "X", "name": "9", "ts": 8366625, "pid": 14, "dur": 0},{"ph": "X", "name": "10", "ts": 8366629, "pid": 14, "dur": 0},{"ph": "X", "name": "11", "ts": 8366632, "pid": 14, "dur": 0},{"ph": "X", "name": "12", "ts": 8366635, "pid": 14, "dur": 0},{"ph": "X", "name": "13", "ts": 8366639, "pid": 14, "dur": 0},{"ph": "X", "name": "14", "ts": 8366642, "pid": 14, "dur": 0},{"ph": "X", "name": "15", "ts": 8366645, "pid": 14, "dur": 0},{"ph": "X", "name": "16", "ts": 8366648, "pid": 14, "dur": 0},{"ph": "X", "name": "17", "ts": 8366652, "pid": 14, "dur": 0},{"ph": "X", "name": "18", "ts": 8366654, "pid": 14, "dur": 0},{"ph": "X", "name": "19", "ts": 8366657, "pid": 14, "dur": 0},{"ph": "X", "name": "20", "ts": 8366660, "pid": 14, "dur": 0},{"ph": "X", "name": "21", "ts": 8366663, "pid": 14, "dur": 0},{"ph": "X", "name": "22", "ts": 8366667, "pid": 14, "dur": 0},{"ph": "X", "name": "23", "ts": 8366670, "pid": 14, "dur": 0},{"ph": "X", "name": "24", "ts": 8366674, "pid": 14, "dur": 0},{"ph": "X", "name": "25", "ts": 8366676, "pid": 14, "dur": 0},{"ph": "X", "name": "26", "ts": 8366679, "pid": 14, "dur": 0},{"ph": "X", "name": "27", "ts": 8366682, "pid": 14, "dur": 0},{"ph": "X", "name": "29", "ts": 8366686, "pid": 14, "dur": 0},{"ph": "X", "name": "30", "ts": 8366690, "pid": 14, "dur": 0},{"ph": "X", "name": "31", "ts": 8366693, "pid": 14, "dur": 0},{"ph": "E", "ts": 8366694, "pid": 14},{"ph": "B", "name": "ALLREDUCE", "ts": 8366736, "pid": 14},{"ph": "B", "name": "WAIT_FOR_DATA", "ts": 8366739, "pid": 14},{"ph": "E", "ts": 8366744, "pid": 14},{"ph": "B", "name": "WAIT_FOR_OTHER_TENSOR_DATA", "ts": 8366747, "pid": 14},{"ph": "E", "ts": 8366805, "pid": 14},{"ph": "B", "name": "QUEUE", "ts": 8366930, "pid": 14},{"ph": "E", "ts": 8366942, "pid": 14},{"ph": "B", "name": "NCCL_ALLREDUCE", "ts": 8366946, "pid": 14},{"ph": "E", "ts": 8367475, "pid": 14},{"ph": "E", "ts": 8367495, "pid": 14, "args": {"dtype": "float32", "shape": "[8192]"}},{"name": "process_name", "ph": "M", "pid": 15, "args": {"name": "allreduce.noname.15"}},
{"name": "process_sort_index", "ph": "M", "pid": 15, "args": {"sort_index": 15}},
{"ph": "B", "name": "NEGOTIATE_ALLREDUCE", "ts": 8368651, "pid": 15},{"ph": "X", "name": "0", "ts": 8368654, "pid": 15, "dur": 0},{"ph": "X", "name": "1", "ts": 8368707, "pid": 15, "dur": 0},{"ph": "X", "name": "5", "ts": 8368714, "pid": 15, "dur": 0},{"ph": "X", "name": "7", "ts": 8368717, "pid": 15, "dur": 0},{"ph": "X", "name": "10", "ts": 8368723, "pid": 15, "dur": 0},{"ph": "X", "name": "11", "ts": 8368726, "pid": 15, "dur": 0},{"ph": "X", "name": "15", "ts": 8368731, "pid": 15, "dur": 0},{"ph": "X", "name": "16", "ts": 8368735, "pid": 15, "dur": 0},{"ph": "X", "name": "20", "ts": 8368740, "pid": 15, "dur": 0},{"ph": "X", "name": "21", "ts": 8368744, "pid": 15, "dur": 0},{"ph": "X", "name": "22", "ts": 8368747, "pid": 15, "dur": 0},{"ph": "X", "name": "23", "ts": 8368751, "pid": 15, "dur": 0},{"ph": "X", "name": "25", "ts": 8368755, "pid": 15, "dur": 0},{"ph": "X", "name": "26", "ts": 8368758, "pid": 15, "dur": 0},{"ph": "X", "name": "27", "ts": 8368762, "pid": 15, "dur": 0},{"ph": "X", "name": "28", "ts": 8368765, "pid": 15, "dur": 0},{"ph": "X", "name": "31", "ts": 8368769, "pid": 15, "dur": 0},{"ph": "X", "name": "2", "ts": 8369751, "pid": 15, "dur": 0},{"ph": "X", "name": "3", "ts": 8369754, "pid": 15, "dur": 0},{"ph": "X", "name": "4", "ts": 8369757, "pid": 15, "dur": 0},{"ph": "X", "name": "6", "ts": 8369762, "pid": 15, "dur": 0},{"ph": "X", "name": "8", "ts": 8369766, "pid": 15, "dur": 0},{"ph": "X", "name": "9", "ts": 8369770, "pid": 15, "dur": 0},{"ph": "X", "name": "12", "ts": 8369774, "pid": 15, "dur": 0},{"ph": "X", "name": "13", "ts": 8369778, "pid": 15, "dur": 0},{"ph": "X", "name": "14", "ts": 8369781, "pid": 15, "dur": 0},{"ph": "X", "name": "17", "ts": 8369785, "pid": 15, "dur": 0},{"ph": "X", "name": "18", "ts": 8369789, "pid": 15, "dur": 0},{"ph": "X", "name": "19", "ts": 8369792, "pid": 15, "dur": 0},{"ph": "X", "name": "24", "ts": 8369798, "pid": 15, "dur": 0},{"ph": "X", "name": "29", "ts": 8369803, "pid": 15, "dur": 0},{"ph": "X", "name": "30", "ts": 8369807, "pid": 15, "dur": 0},{"ph": "E", "ts": 8369809, "pid": 15},{"ph": "B", "name": "ALLREDUCE", "ts": 8369850, "pid": 15},{"ph": "B", "name": "WAIT_FOR_DATA", "ts": 8369852, "pid": 15},{"ph": "E", "ts": 8369858, "pid": 15},{"ph": "B", "name": "WAIT_FOR_OTHER_TENSOR_DATA", "ts": 8369861, "pid": 15},{"ph": "E", "ts": 8369920, "pid": 15},{"ph": "B", "name": "QUEUE", "ts": 8370047, "pid": 15},{"ph": "E", "ts": 8370057, "pid": 15},{"ph": "B", "name": "NCCL_ALLREDUCE", "ts": 8370062, "pid": 15},{"ph": "E", "ts": 8370267, "pid": 15},{"ph": "E", "ts": 8370288, "pid": 15, "args": {"dtype": "float32", "shape": "[16384]"}},{"name": "process_name", "ph": "M", "pid": 16, "args": {"name": "allreduce.noname.16"}},
{"name": "process_sort_index", "ph": "M", "pid": 16, "args": {"sort_index": 16}},
{"ph": "B", "name": "NEGOTIATE_ALLREDUCE", "ts": 8371834, "pid": 16},{"ph": "X", "name": "0", "ts": 8371837, "pid": 16, "dur": 0},{"ph": "X", "name": "2", "ts": 8371896, "pid": 16, "dur": 0},{"ph": "X", "name": "3", "ts": 8371899, "pid": 16, "dur": 0},{"ph": "X", "name": "4", "ts": 8371902, "pid": 16, "dur": 0},{"ph": "X", "name": "5", "ts": 8371905, "pid": 16, "dur": 0},{"ph": "X", "name": "7", "ts": 8371909, "pid": 16, "dur": 0},{"ph": "X", "name": "8", "ts": 8371913, "pid": 16, "dur": 0},{"ph": "X", "name": "9", "ts": 8371916, "pid": 16, "dur": 0},{"ph": "X", "name": "10", "ts": 8371920, "pid": 16, "dur": 0},{"ph": "X", "name": "11", "ts": 8371924, "pid": 16, "dur": 0},{"ph": "X", "name": "12", "ts": 8371928, "pid": 16, "dur": 0},{"ph": "X", "name": "13", "ts": 8371931, "pid": 16, "dur": 0},{"ph": "X", "name": "14", "ts": 8371934, "pid": 16, "dur": 0},{"ph": "X", "name": "15", "ts": 8371938, "pid": 16, "dur": 0},{"ph": "X", "name": "16", "ts": 8371941, "pid": 16, "dur": 0},{"ph": "X", "name": "20", "ts": 8371946, "pid": 16, "dur": 0},{"ph": "X", "name": "22", "ts": 8371951, "pid": 16, "dur": 0},{"ph": "X", "name": "23", "ts": 8371954, "pid": 16, "dur": 0},{"ph": "X", "name": "25", "ts": 8371957, "pid": 16, "dur": 0},{"ph": "X", "name": "26", "ts": 8371960, "pid": 16, "dur": 0},{"ph": "X", "name": "27", "ts": 8371963, "pid": 16, "dur": 0},{"ph": "X", "name": "28", "ts": 8371967, "pid": 16, "dur": 0},{"ph": "X", "name": "29", "ts": 8371969, "pid": 16, "dur": 0},{"ph": "X", "name": "30", "ts": 8371972, "pid": 16, "dur": 0},{"ph": "X", "name": "31", "ts": 8371976, "pid": 16, "dur": 0},{"ph": "X", "name": "1", "ts": 8372986, "pid": 16, "dur": 0},{"ph": "X", "name": "6", "ts": 8372993, "pid": 16, "dur": 0},{"ph": "X", "name": "17", "ts": 8373004, "pid": 16, "dur": 0},{"ph": "X", "name": "18", "ts": 8373007, "pid": 16, "dur": 0},{"ph": "X", "name": "19", "ts": 8373010, "pid": 16, "dur": 0},{"ph": "X", "name": "21", "ts": 8373018, "pid": 16, "dur": 0},{"ph": "X", "name": "24", "ts": 8373023, "pid": 16, "dur": 0},{"ph": "E", "ts": 8373026, "pid": 16},{"ph": "B", "name": "ALLREDUCE", "ts": 8373070, "pid": 16},{"ph": "B", "name": "WAIT_FOR_DATA", "ts": 8373073, "pid": 16},{"ph": "E", "ts": 8373078, "pid": 16},{"ph": "B", "name": "WAIT_FOR_OTHER_TENSOR_DATA", "ts": 8373081, "pid": 16},{"ph": "E", "ts": 8373140, "pid": 16},{"ph": "B", "name": "QUEUE", "ts": 8373204, "pid": 16},{"ph": "E", "ts": 8373214, "pid": 16},{"ph": "B", "name": "NCCL_ALLREDUCE", "ts": 8373219, "pid": 16},{"ph": "E", "ts": 8373567, "pid": 16},{"ph": "E", "ts": 8373588, "pid": 16, "args": {"dtype": "float32", "shape": "[32768]"}},{"name": "process_name", "ph": "M", "pid": 17, "args": {"name": "allreduce.noname.17"}},
{"name": "process_sort_index", "ph": "M", "pid": 17, "args": {"sort_index": 17}},
{"ph": "B", "name": "NEGOTIATE_ALLREDUCE", "ts": 8375175, "pid": 17},{"ph": "X", "name": "28", "ts": 8375177, "pid": 17, "dur": 0},{"ph": "X", "name": "0", "ts": 8376174, "pid": 17, "dur": 0},{"ph": "X", "name": "1", "ts": 8376233, "pid": 17, "dur": 0},{"ph": "X", "name": "2", "ts": 8376236, "pid": 17, "dur": 0},{"ph": "X", "name": "3", "ts": 8376239, "pid": 17, "dur": 0},{"ph": "X", "name": "4", "ts": 8376242, "pid": 17, "dur": 0},{"ph": "X", "name": "5", "ts": 8376246, "pid": 17, "dur": 0},{"ph": "X", "name": "6", "ts": 8376250, "pid": 17, "dur": 0},{"ph": "X", "name": "7", "ts": 8376253, "pid": 17, "dur": 0},{"ph": "X", "name": "8", "ts": 8376257, "pid": 17, "dur": 0},{"ph": "X", "name": "9", "ts": 8376260, "pid": 17, "dur": 0},{"ph": "X", "name": "10", "ts": 8376264, "pid": 17, "dur": 0},{"ph": "X", "name": "11", "ts": 8376268, "pid": 17, "dur": 0},{"ph": "X", "name": "12", "ts": 8376271, "pid": 17, "dur": 0},{"ph": "X", "name": "13", "ts": 8376275, "pid": 17, "dur": 0},{"ph": "X", "name": "14", "ts": 8376278, "pid": 17, "dur": 0},{"ph": "X", "name": "15", "ts": 8376281, "pid": 17, "dur": 0},{"ph": "X", "name": "16", "ts": 8376283, "pid": 17, "dur": 0},{"ph": "X", "name": "19", "ts": 8376288, "pid": 17, "dur": 0},{"ph": "X", "name": "20", "ts": 8376291, "pid": 17, "dur": 0},{"ph": "X", "name": "22", "ts": 8376295, "pid": 17, "dur": 0},{"ph": "X", "name": "23", "ts": 8376298, "pid": 17, "dur": 0},{"ph": "X", "name": "24", "ts": 8376301, "pid": 17, "dur": 0},{"ph": "X", "name": "26", "ts": 8376305, "pid": 17, "dur": 0},{"ph": "X", "name": "27", "ts": 8376308, "pid": 17, "dur": 0},{"ph": "X", "name": "29", "ts": 8376313, "pid": 17, "dur": 0},{"ph": "X", "name": "30", "ts": 8376316, "pid": 17, "dur": 0},{"ph": "X", "name": "31", "ts": 8376319, "pid": 17, "dur": 0},{"ph": "X", "name": "17", "ts": 8377331, "pid": 17, "dur": 0},{"ph": "X", "name": "18", "ts": 8377334, "pid": 17, "dur": 0},{"ph": "X", "name": "21", "ts": 8377338, "pid": 17, "dur": 0},{"ph": "X", "name": "25", "ts": 8377343, "pid": 17, "dur": 0},{"ph": "E", "ts": 8377346, "pid": 17},{"ph": "B", "name": "ALLREDUCE", "ts": 8377388, "pid": 17},{"ph": "B", "name": "WAIT_FOR_DATA", "ts": 8377390, "pid": 17},{"ph": "E", "ts": 8377395, "pid": 17},{"ph": "B", "name": "WAIT_FOR_OTHER_TENSOR_DATA", "ts": 8377398, "pid": 17},{"ph": "E", "ts": 8377457, "pid": 17},{"ph": "B", "name": "QUEUE", "ts": 8377575, "pid": 17},{"ph": "E", "ts": 8377585, "pid": 17},{"ph": "B", "name": "NCCL_ALLREDUCE", "ts": 8377590, "pid": 17},{"ph": "E", "ts": 8378262, "pid": 17},{"ph": "E", "ts": 8378286, "pid": 17, "args": {"dtype": "float32", "shape": "[65536]"}},{"name": "process_name", "ph": "M", "pid": 18, "args": {"name": "allreduce.noname.18"}},
{"name": "process_sort_index", "ph": "M", "pid": 18, "args": {"sort_index": 18}},
{"ph": "B", "name": "NEGOTIATE_ALLREDUCE", "ts": 8380510, "pid": 18},{"ph": "X", "name": "28", "ts": 8380512, "pid": 18, "dur": 0},{"ph": "X", "name": "0", "ts": 8381592, "pid": 18, "dur": 0},{"ph": "X", "name": "1", "ts": 8381634, "pid": 18, "dur": 0},{"ph": "X", "name": "2", "ts": 8381638, "pid": 18, "dur": 0},{"ph": "X", "name": "3", "ts": 8381641, "pid": 18, "dur": 0},{"ph": "X", "name": "4", "ts": 8381644, "pid": 18, "dur": 0},{"ph": "X", "name": "5", "ts": 8381647, "pid": 18, "dur": 0},{"ph": "X", "name": "6", "ts": 8381651, "pid": 18, "dur": 0},{"ph": "X", "name": "7", "ts": 8381655, "pid": 18, "dur": 0},{"ph": "X", "name": "8", "ts": 8381658, "pid": 18, "dur": 0},{"ph": "X", "name": "9", "ts": 8381661, "pid": 18, "dur": 0},{"ph": "X", "name": "10", "ts": 8381665, "pid": 18, "dur": 0},{"ph": "X", "name": "11", "ts": 8381669, "pid": 18, "dur": 0},{"ph": "X", "name": "12", "ts": 8381671, "pid": 18, "dur": 0},{"ph": "X", "name": "13", "ts": 8381676, "pid": 18, "dur": 0},{"ph": "X", "name": "14", "ts": 8381683, "pid": 18, "dur": 0},{"ph": "X", "name": "15", "ts": 8381686, "pid": 18, "dur": 0},{"ph": "X", "name": "16", "ts": 8381689, "pid": 18, "dur": 0},{"ph": "X", "name": "17", "ts": 8381692, "pid": 18, "dur": 0},{"ph": "X", "name": "20", "ts": 8381697, "pid": 18, "dur": 0},{"ph": "X", "name": "23", "ts": 8381702, "pid": 18, "dur": 0},{"ph": "X", "name": "26", "ts": 8381707, "pid": 18, "dur": 0},{"ph": "X", "name": "27", "ts": 8381710, "pid": 18, "dur": 0},{"ph": "X", "name": "29", "ts": 8381713, "pid": 18, "dur": 0},{"ph": "X", "name": "30", "ts": 8381717, "pid": 18, "dur": 0},{"ph": "X", "name": "31", "ts": 8381721, "pid": 18, "dur": 0},{"ph": "X", "name": "18", "ts": 8382711, "pid": 18, "dur": 0},{"ph": "X", "name": "19", "ts": 8382714, "pid": 18, "dur": 0},{"ph": "X", "name": "24", "ts": 8382721, "pid": 18, "dur": 0},{"ph": "X", "name": "22", "ts": 8383834, "pid": 18, "dur": 0},{"ph": "X", "name": "21", "ts": 8384930, "pid": 18, "dur": 0},{"ph": "X", "name": "25", "ts": 8384935, "pid": 18, "dur": 0},{"ph": "E", "ts": 8384937, "pid": 18},{"ph": "B", "name": "ALLREDUCE", "ts": 8384976, "pid": 18},{"ph": "B", "name": "WAIT_FOR_DATA", "ts": 8384979, "pid": 18},{"ph": "E", "ts": 8384984, "pid": 18},{"ph": "B", "name": "WAIT_FOR_OTHER_TENSOR_DATA", "ts": 8384987, "pid": 18},{"ph": "E", "ts": 8385046, "pid": 18},{"ph": "B", "name": "QUEUE", "ts": 8385159, "pid": 18},{"ph": "E", "ts": 8385171, "pid": 18},{"ph": "B", "name": "NCCL_ALLREDUCE", "ts": 8385176, "pid": 18},{"ph": "E", "ts": 8385728, "pid": 18},{"ph": "E", "ts": 8385754, "pid": 18, "args": {"dtype": "float32", "shape": "[131072]"}},{"name": "process_name", "ph": "M", "pid": 19, "args": {"name": "allreduce.noname.19"}},
{"name": "process_sort_index", "ph": "M", "pid": 19, "args": {"sort_index": 19}},
{"ph": "B", "name": "NEGOTIATE_ALLREDUCE", "ts": 8390436, "pid": 19},{"ph": "X", "name": "28", "ts": 8390438, "pid": 19, "dur": 0},{"ph": "X", "name": "0", "ts": 8391466, "pid": 19, "dur": 0},{"ph": "X", "name": "3", "ts": 8391510, "pid": 19, "dur": 0},{"ph": "X", "name": "4", "ts": 8391513, "pid": 19, "dur": 0},{"ph": "X", "name": "6", "ts": 8391518, "pid": 19, "dur": 0},{"ph": "X", "name": "7", "ts": 8391522, "pid": 19, "dur": 0},{"ph": "X", "name": "8", "ts": 8391525, "pid": 19, "dur": 0},{"ph": "X", "name": "9", "ts": 8391529, "pid": 19, "dur": 0},{"ph": "X", "name": "10", "ts": 8391532, "pid": 19, "dur": 0},{"ph": "X", "name": "11", "ts": 8391536, "pid": 19, "dur": 0},{"ph": "X", "name": "12", "ts": 8391539, "pid": 19, "dur": 0},{"ph": "X", "name": "13", "ts": 8391543, "pid": 19, "dur": 0},{"ph": "X", "name": "14", "ts": 8391547, "pid": 19, "dur": 0},{"ph": "X", "name": "15", "ts": 8391549, "pid": 19, "dur": 0},{"ph": "X", "name": "16", "ts": 8391553, "pid": 19, "dur": 0},{"ph": "X", "name": "17", "ts": 8391556, "pid": 19, "dur": 0},{"ph": "X", "name": "20", "ts": 8391561, "pid": 19, "dur": 0},{"ph": "X", "name": "21", "ts": 8391564, "pid": 19, "dur": 0},{"ph": "X", "name": "23", "ts": 8391568, "pid": 19, "dur": 0},{"ph": "X", "name": "25", "ts": 8391571, "pid": 19, "dur": 0},{"ph": "X", "name": "26", "ts": 8391574, "pid": 19, "dur": 0},{"ph": "X", "name": "27", "ts": 8391578, "pid": 19, "dur": 0},{"ph": "X", "name": "29", "ts": 8391582, "pid": 19, "dur": 0},{"ph": "X", "name": "30", "ts": 8391585, "pid": 19, "dur": 0},{"ph": "X", "name": "31", "ts": 8391589, "pid": 19, "dur": 0},{"ph": "X", "name": "1", "ts": 8392608, "pid": 19, "dur": 0},{"ph": "X", "name": "2", "ts": 8392611, "pid": 19, "dur": 0},{"ph": "X", "name": "5", "ts": 8392616, "pid": 19, "dur": 0},{"ph": "X", "name": "24", "ts": 8392633, "pid": 19, "dur": 0},{"ph": "X", "name": "18", "ts": 8393721, "pid": 19, "dur": 0},{"ph": "X", "name": "19", "ts": 8393725, "pid": 19, "dur": 0},{"ph": "X", "name": "22", "ts": 8394786, "pid": 19, "dur": 0},{"ph": "E", "ts": 8394788, "pid": 19},{"ph": "B", "name": "ALLREDUCE", "ts": 8394828, "pid": 19},{"ph": "B", "name": "WAIT_FOR_DATA", "ts": 8394831, "pid": 19},{"ph": "E", "ts": 8394836, "pid": 19},{"ph": "B", "name": "WAIT_FOR_OTHER_TENSOR_DATA", "ts": 8394839, "pid": 19},{"ph": "E", "ts": 8394897, "pid": 19},{"ph": "B", "name": "QUEUE", "ts": 8395028, "pid": 19},{"ph": "E", "ts": 8395039, "pid": 19},{"ph": "B", "name": "NCCL_ALLREDUCE", "ts": 8395046, "pid": 19},{"ph": "E", "ts": 8395851, "pid": 19},{"ph": "E", "ts": 8395877, "pid": 19, "args": {"dtype": "float32", "shape": "[262144]"}},{"name": "process_name", "ph": "M", "pid": 20, "args": {"name": "allreduce.noname.20"}},
{"name": "process_sort_index", "ph": "M", "pid": 20, "args": {"sort_index": 20}},
{"ph": "B", "name": "NEGOTIATE_ALLREDUCE", "ts": 8403584, "pid": 20},{"ph": "X", "name": "0", "ts": 8403589, "pid": 20, "dur": 0},{"ph": "X", "name": "4", "ts": 8403689, "pid": 20, "dur": 0},{"ph": "X", "name": "10", "ts": 8403695, "pid": 20, "dur": 0},{"ph": "X", "name": "11", "ts": 8403698, "pid": 20, "dur": 0},{"ph": "X", "name": "14", "ts": 8403703, "pid": 20, "dur": 0},{"ph": "X", "name": "15", "ts": 8403706, "pid": 20, "dur": 0},{"ph": "X", "name": "16", "ts": 8403710, "pid": 20, "dur": 0},{"ph": "X", "name": "22", "ts": 8403716, "pid": 20, "dur": 0},{"ph": "X", "name": "23", "ts": 8403720, "pid": 20, "dur": 0},{"ph": "X", "name": "26", "ts": 8403725, "pid": 20, "dur": 0},{"ph": "X", "name": "28", "ts": 8403729, "pid": 20, "dur": 0},{"ph": "X", "name": "2", "ts": 8404557, "pid": 20, "dur": 0},{"ph": "X", "name": "3", "ts": 8404560, "pid": 20, "dur": 0},{"ph": "X", "name": "6", "ts": 8404565, "pid": 20, "dur": 0},{"ph": "X", "name": "9", "ts": 8404569, "pid": 20, "dur": 0},{"ph": "X", "name": "12", "ts": 8404573, "pid": 20, "dur": 0},{"ph": "X", "name": "13", "ts": 8404577, "pid": 20, "dur": 0},{"ph": "X", "name": "17", "ts": 8404582, "pid": 20, "dur": 0},{"ph": "X", "name": "19", "ts": 8404586, "pid": 20, "dur": 0},{"ph": "X", "name": "20", "ts": 8404589, "pid": 20, "dur": 0},{"ph": "X", "name": "21", "ts": 8404593, "pid": 20, "dur": 0},{"ph": "X", "name": "27", "ts": 8404600, "pid": 20, "dur": 0},{"ph": "X", "name": "29", "ts": 8404603, "pid": 20, "dur": 0},{"ph": "X", "name": "31", "ts": 8404607, "pid": 20, "dur": 0},{"ph": "X", "name": "8", "ts": 8405707, "pid": 20, "dur": 0},{"ph": "X", "name": "24", "ts": 8405720, "pid": 20, "dur": 0},{"ph": "X", "name": "25", "ts": 8405723, "pid": 20, "dur": 0},{"ph": "X", "name": "30", "ts": 8405729, "pid": 20, "dur": 0},{"ph": "X", "name": "7", "ts": 8409000, "pid": 20, "dur": 0},{"ph": "X", "name": "1", "ts": 8410108, "pid": 20, "dur": 0},{"ph": "X", "name": "5", "ts": 8410113, "pid": 20, "dur": 0},{"ph": "X", "name": "18", "ts": 8413406, "pid": 20, "dur": 0},{"ph": "E", "ts": 8413408, "pid": 20},{"ph": "B", "name": "ALLREDUCE", "ts": 8413452, "pid": 20},{"ph": "B", "name": "WAIT_FOR_DATA", "ts": 8413454, "pid": 20},{"ph": "E", "ts": 8413459, "pid": 20},{"ph": "B", "name": "WAIT_FOR_OTHER_TENSOR_DATA", "ts": 8413462, "pid": 20},{"ph": "E", "ts": 8413520, "pid": 20},{"ph": "B", "name": "QUEUE", "ts": 8413650, "pid": 20},{"ph": "E", "ts": 8413663, "pid": 20},{"ph": "B", "name": "NCCL_ALLREDUCE", "ts": 8413670, "pid": 20},{"ph": "E", "ts": 8414789, "pid": 20},{"ph": "E", "ts": 8414817, "pid": 20, "args": {"dtype": "float32", "shape": "[524288]"}},{"name": "process_name", "ph": "M", "pid": 21, "args": {"name": "allreduce.noname.21"}},
{"name": "process_sort_index", "ph": "M", "pid": 21, "args": {"sort_index": 21}},
{"ph": "B", "name": "NEGOTIATE_ALLREDUCE", "ts": 8427553, "pid": 21},{"ph": "X", "name": "0", "ts": 8427555, "pid": 21, "dur": 0},{"ph": "X", "name": "4", "ts": 8427589, "pid": 21, "dur": 0},{"ph": "X", "name": "10", "ts": 8427596, "pid": 21, "dur": 0},{"ph": "X", "name": "22", "ts": 8427606, "pid": 21, "dur": 0},{"ph": "X", "name": "26", "ts": 8427611, "pid": 21, "dur": 0},{"ph": "X", "name": "29", "ts": 8427617, "pid": 21, "dur": 0},{"ph": "X", "name": "31", "ts": 8427621, "pid": 21, "dur": 0},{"ph": "X", "name": "3", "ts": 8428691, "pid": 21, "dur": 0},{"ph": "X", "name": "8", "ts": 8428697, "pid": 21, "dur": 0},{"ph": "X", "name": "13", "ts": 8428703, "pid": 21, "dur": 0},{"ph": "X", "name": "16", "ts": 8428708, "pid": 21, "dur": 0},{"ph": "X", "name": "18", "ts": 8428712, "pid": 21, "dur": 0},{"ph": "X", "name": "27", "ts": 8428721, "pid": 21, "dur": 0},{"ph": "X", "name": "28", "ts": 8428725, "pid": 21, "dur": 0},{"ph": "X", "name": "5", "ts": 8429795, "pid": 21, "dur": 0},{"ph": "X", "name": "6", "ts": 8429799, "pid": 21, "dur": 0},{"ph": "X", "name": "7", "ts": 8429802, "pid": 21, "dur": 0},{"ph": "X", "name": "11", "ts": 8429808, "pid": 21, "dur": 0},{"ph": "X", "name": "12", "ts": 8429812, "pid": 21, "dur": 0},{"ph": "X", "name": "17", "ts": 8429818, "pid": 21, "dur": 0},{"ph": "X", "name": "19", "ts": 8429821, "pid": 21, "dur": 0},{"ph": "X", "name": "20", "ts": 8429825, "pid": 21, "dur": 0},{"ph": "X", "name": "23", "ts": 8429829, "pid": 21, "dur": 0},{"ph": "X", "name": "24", "ts": 8429833, "pid": 21, "dur": 0},{"ph": "X", "name": "1", "ts": 8430820, "pid": 21, "dur": 0},{"ph": "X", "name": "9", "ts": 8430831, "pid": 21, "dur": 0},{"ph": "X", "name": "21", "ts": 8430842, "pid": 21, "dur": 0},{"ph": "X", "name": "2", "ts": 8431946, "pid": 21, "dur": 0},{"ph": "X", "name": "25", "ts": 8431964, "pid": 21, "dur": 0},{"ph": "X", "name": "30", "ts": 8437486, "pid": 21, "dur": 0},{"ph": "X", "name": "14", "ts": 8438593, "pid": 21, "dur": 0},{"ph": "X", "name": "15", "ts": 8438596, "pid": 21, "dur": 0},{"ph": "E", "ts": 8438598, "pid": 21},{"ph": "B", "name": "ALLREDUCE", "ts": 8438644, "pid": 21},{"ph": "B", "name": "WAIT_FOR_DATA", "ts": 8438646, "pid": 21},{"ph": "E", "ts": 8438651, "pid": 21},{"ph": "B", "name": "WAIT_FOR_OTHER_TENSOR_DATA", "ts": 8438654, "pid": 21},{"ph": "E", "ts": 8438711, "pid": 21},{"ph": "B", "name": "QUEUE", "ts": 8438858, "pid": 21},{"ph": "E", "ts": 8438873, "pid": 21},{"ph": "B", "name": "NCCL_ALLREDUCE", "ts": 8438881, "pid": 21},{"ph": "E", "ts": 8440699, "pid": 21},{"ph": "E", "ts": 8440731, "pid": 21, "args": {"dtype": "float32", "shape": "[1048576]"}},{"name": "process_name", "ph": "M", "pid": 22, "args": {"name": "allreduce.noname.22"}},
{"name": "process_sort_index", "ph": "M", "pid": 22, "args": {"sort_index": 22}},
{"ph": "B", "name": "NEGOTIATE_ALLREDUCE", "ts": 8464897, "pid": 22},{"ph": "X", "name": "0", "ts": 8464899, "pid": 22, "dur": 0},{"ph": "X", "name": "10", "ts": 8464931, "pid": 22, "dur": 0},{"ph": "X", "name": "31", "ts": 8464944, "pid": 22, "dur": 0},{"ph": "X", "name": "11", "ts": 8466049, "pid": 22, "dur": 0},{"ph": "X", "name": "13", "ts": 8466052, "pid": 22, "dur": 0},{"ph": "X", "name": "16", "ts": 8466056, "pid": 22, "dur": 0},{"ph": "X", "name": "23", "ts": 8466062, "pid": 22, "dur": 0},{"ph": "X", "name": "26", "ts": 8466066, "pid": 22, "dur": 0},{"ph": "X", "name": "4", "ts": 8467221, "pid": 22, "dur": 0},{"ph": "X", "name": "17", "ts": 8467231, "pid": 22, "dur": 0},{"ph": "X", "name": "18", "ts": 8467235, "pid": 22, "dur": 0},{"ph": "X", "name": "19", "ts": 8467238, "pid": 22, "dur": 0},{"ph": "X", "name": "20", "ts": 8467242, "pid": 22, "dur": 0},{"ph": "X", "name": "24", "ts": 8467246, "pid": 22, "dur": 0},{"ph": "X", "name": "27", "ts": 8467250, "pid": 22, "dur": 0},{"ph": "X", "name": "28", "ts": 8467253, "pid": 22, "dur": 0},{"ph": "X", "name": "5", "ts": 8468273, "pid": 22, "dur": 0},{"ph": "X", "name": "22", "ts": 8468284, "pid": 22, "dur": 0},{"ph": "X", "name": "29", "ts": 8468290, "pid": 22, "dur": 0},{"ph": "X", "name": "7", "ts": 8469403, "pid": 22, "dur": 0},{"ph": "X", "name": "12", "ts": 8469408, "pid": 22, "dur": 0},{"ph": "X", "name": "14", "ts": 8469411, "pid": 22, "dur": 0},{"ph": "X", "name": "1", "ts": 8470522, "pid": 22, "dur": 0},{"ph": "X", "name": "2", "ts": 8470525, "pid": 22, "dur": 0},{"ph": "X", "name": "6", "ts": 8470529, "pid": 22, "dur": 0},{"ph": "X", "name": "21", "ts": 8470539, "pid": 22, "dur": 0},{"ph": "X", "name": "30", "ts": 8470546, "pid": 22, "dur": 0},{"ph": "X", "name": "15", "ts": 8471635, "pid": 22, "dur": 0},{"ph": "X", "name": "25", "ts": 8471642, "pid": 22, "dur": 0},{"ph": "X", "name": "3", "ts": 8477189, "pid": 22, "dur": 0},{"ph": "X", "name": "8", "ts": 8479414, "pid": 22, "dur": 0},{"ph": "X", "name": "9", "ts": 8483879, "pid": 22, "dur": 0},{"ph": "E", "ts": 8483881, "pid": 22},{"ph": "B", "name": "ALLREDUCE", "ts": 8483931, "pid": 22},{"ph": "B", "name": "WAIT_FOR_DATA", "ts": 8483934, "pid": 22},{"ph": "E", "ts": 8483940, "pid": 22},{"ph": "B", "name": "WAIT_FOR_OTHER_TENSOR_DATA", "ts": 8483942, "pid": 22},{"ph": "E", "ts": 8483999, "pid": 22},{"ph": "B", "name": "QUEUE", "ts": 8484140, "pid": 22},{"ph": "E", "ts": 8484158, "pid": 22},{"ph": "B", "name": "NCCL_ALLREDUCE", "ts": 8484167, "pid": 22},{"ph": "E", "ts": 8487225, "pid": 22},{"ph": "E", "ts": 8487278, "pid": 22, "args": {"dtype": "float32", "shape": "[2097152]"}},{"name": "process_name", "ph": "M", "pid": 23, "args": {"name": "allreduce.noname.23"}},
{"name": "process_sort_index", "ph": "M", "pid": 23, "args": {"sort_index": 23}},
{"ph": "B", "name": "NEGOTIATE_ALLREDUCE", "ts": 8536215, "pid": 23},{"ph": "X", "name": "4", "ts": 8536217, "pid": 23, "dur": 0},{"ph": "X", "name": "6", "ts": 8536222, "pid": 23, "dur": 0},{"ph": "X", "name": "11", "ts": 8537290, "pid": 23, "dur": 0},{"ph": "X", "name": "13", "ts": 8537293, "pid": 23, "dur": 0},{"ph": "X", "name": "23", "ts": 8537301, "pid": 23, "dur": 0},{"ph": "X", "name": "10", "ts": 8538417, "pid": 23, "dur": 0},{"ph": "X", "name": "12", "ts": 8538420, "pid": 23, "dur": 0},{"ph": "X", "name": "20", "ts": 8538428, "pid": 23, "dur": 0},{"ph": "X", "name": "27", "ts": 8538434, "pid": 23, "dur": 0},{"ph": "X", "name": "28", "ts": 8538437, "pid": 23, "dur": 0},{"ph": "X", "name": "29", "ts": 8538439, "pid": 23, "dur": 0},{"ph": "X", "name": "17", "ts": 8539516, "pid": 23, "dur": 0},{"ph": "X", "name": "18", "ts": 8539518, "pid": 23, "dur": 0},{"ph": "X", "name": "19", "ts": 8539521, "pid": 23, "dur": 0},{"ph": "X", "name": "0", "ts": 8541714, "pid": 23, "dur": 0},{"ph": "X", "name": "5", "ts": 8541744, "pid": 23, "dur": 0},{"ph": "X", "name": "16", "ts": 8541752, "pid": 23, "dur": 0},{"ph": "X", "name": "26", "ts": 8541759, "pid": 23, "dur": 0},{"ph": "X", "name": "31", "ts": 8541765, "pid": 23, "dur": 0},{"ph": "X", "name": "7", "ts": 8542846, "pid": 23, "dur": 0},{"ph": "X", "name": "15", "ts": 8545098, "pid": 23, "dur": 0},{"ph": "X", "name": "1", "ts": 8546192, "pid": 23, "dur": 0},{"ph": "X", "name": "21", "ts": 8546206, "pid": 23, "dur": 0},{"ph": "X", "name": "25", "ts": 8546210, "pid": 23, "dur": 0},{"ph": "X", "name": "30", "ts": 8546216, "pid": 23, "dur": 0},{"ph": "X", "name": "2", "ts": 8547312, "pid": 23, "dur": 0},{"ph": "X", "name": "3", "ts": 8547315, "pid": 23, "dur": 0},{"ph": "X", "name": "22", "ts": 8547328, "pid": 23, "dur": 0},{"ph": "X", "name": "9", "ts": 8549538, "pid": 23, "dur": 0},{"ph": "X", "name": "8", "ts": 8551759, "pid": 23, "dur": 0},{"ph": "X", "name": "14", "ts": 8552873, "pid": 23, "dur": 0},{"ph": "X", "name": "24", "ts": 8556232, "pid": 23, "dur": 0},{"ph": "E", "ts": 8556233, "pid": 23},{"ph": "B", "name": "ALLREDUCE", "ts": 8556276, "pid": 23},{"ph": "B", "name": "WAIT_FOR_DATA", "ts": 8556278, "pid": 23},{"ph": "E", "ts": 8556286, "pid": 23},{"ph": "B", "name": "WAIT_FOR_OTHER_TENSOR_DATA", "ts": 8556288, "pid": 23},{"ph": "E", "ts": 8556345, "pid": 23},{"ph": "B", "name": "QUEUE", "ts": 8556501, "pid": 23},{"ph": "E", "ts": 8556520, "pid": 23},{"ph": "B", "name": "NCCL_ALLREDUCE", "ts": 8556530, "pid": 23},{"ph": "E", "ts": 8562406, "pid": 23},{"ph": "E", "ts": 8562442, "pid": 23, "args": {"dtype": "float32", "shape": "[4194304]"}},{"name": "process_name", "ph": "M", "pid": 24, "args": {"name": "allreduce.noname.24"}},
{"name": "process_sort_index", "ph": "M", "pid": 24, "args": {"sort_index": 24}},
{"ph": "B", "name": "NEGOTIATE_ALLREDUCE", "ts": 8658440, "pid": 24},{"ph": "X", "name": "7", "ts": 8658442, "pid": 24, "dur": 0},{"ph": "X", "name": "6", "ts": 8659518, "pid": 24, "dur": 0},{"ph": "X", "name": "4", "ts": 8660624, "pid": 24, "dur": 0},{"ph": "X", "name": "5", "ts": 8660627, "pid": 24, "dur": 0},{"ph": "X", "name": "10", "ts": 8661736, "pid": 24, "dur": 0},{"ph": "X", "name": "11", "ts": 8661741, "pid": 24, "dur": 0},{"ph": "X", "name": "12", "ts": 8662865, "pid": 24, "dur": 0},{"ph": "X", "name": "13", "ts": 8662868, "pid": 24, "dur": 0},{"ph": "X", "name": "9", "ts": 8665098, "pid": 24, "dur": 0},{"ph": "X", "name": "0", "ts": 8670624, "pid": 24, "dur": 0},{"ph": "X", "name": "29", "ts": 8670669, "pid": 24, "dur": 0},{"ph": "X", "name": "8", "ts": 8671800, "pid": 24, "dur": 0},{"ph": "X", "name": "20", "ts": 8671809, "pid": 24, "dur": 0},{"ph": "X", "name": "22", "ts": 8671812, "pid": 24, "dur": 0},{"ph": "X", "name": "28", "ts": 8671817, "pid": 24, "dur": 0},{"ph": "X", "name": "16", "ts": 8672881, "pid": 24, "dur": 0},{"ph": "X", "name": "17", "ts": 8672884, "pid": 24, "dur": 0},{"ph": "X", "name": "18", "ts": 8672886, "pid": 24, "dur": 0},{"ph": "X", "name": "19", "ts": 8672889, "pid": 24, "dur": 0},{"ph": "X", "name": "26", "ts": 8672895, "pid": 24, "dur": 0},{"ph": "X", "name": "14", "ts": 8674005, "pid": 24, "dur": 0},{"ph": "X", "name": "24", "ts": 8674012, "pid": 24, "dur": 0},{"ph": "X", "name": "25", "ts": 8674015, "pid": 24, "dur": 0},{"ph": "X", "name": "27", "ts": 8674019, "pid": 24, "dur": 0},{"ph": "X", "name": "31", "ts": 8678465, "pid": 24, "dur": 0},{"ph": "X", "name": "21", "ts": 8681786, "pid": 24, "dur": 0},{"ph": "X", "name": "1", "ts": 8686230, "pid": 24, "dur": 0},{"ph": "X", "name": "30", "ts": 8686248, "pid": 24, "dur": 0},{"ph": "X", "name": "15", "ts": 8687349, "pid": 24, "dur": 0},{"ph": "X", "name": "2", "ts": 8688457, "pid": 24, "dur": 0},{"ph": "X", "name": "3", "ts": 8688460, "pid": 24, "dur": 0},{"ph": "X", "name": "23", "ts": 8697368, "pid": 24, "dur": 0},{"ph": "E", "ts": 8697370, "pid": 24},{"ph": "B", "name": "ALLREDUCE", "ts": 8697423, "pid": 24},{"ph": "B", "name": "WAIT_FOR_DATA", "ts": 8697426, "pid": 24},{"ph": "E", "ts": 8697434, "pid": 24},{"ph": "B", "name": "WAIT_FOR_OTHER_TENSOR_DATA", "ts": 8697437, "pid": 24},{"ph": "E", "ts": 8697495, "pid": 24},{"ph": "B", "name": "QUEUE", "ts": 8697644, "pid": 24},{"ph": "E", "ts": 8697663, "pid": 24},{"ph": "B", "name": "NCCL_ALLREDUCE", "ts": 8697671, "pid": 24},{"ph": "E", "ts": 8709359, "pid": 24},{"ph": "E", "ts": 8709399, "pid": 24, "args": {"dtype": "float32", "shape": "[8388608]"}},{"name": "process_name", "ph": "M", "pid": 25, "args": {"name": "allreduce.noname.25"}},
{"name": "process_sort_index", "ph": "M", "pid": 25, "args": {"sort_index": 25}},
{"ph": "B", "name": "NEGOTIATE_ALLREDUCE", "ts": 8895580, "pid": 25},{"ph": "X", "name": "5", "ts": 8895593, "pid": 25, "dur": 0},{"ph": "X", "name": "8", "ts": 8895598, "pid": 25, "dur": 0},{"ph": "X", "name": "15", "ts": 8896673, "pid": 25, "dur": 0},{"ph": "X", "name": "7", "ts": 8898908, "pid": 25, "dur": 0},{"ph": "X", "name": "4", "ts": 8902245, "pid": 25, "dur": 0},{"ph": "X", "name": "6", "ts": 8902248, "pid": 25, "dur": 0},{"ph": "X", "name": "9", "ts": 8904475, "pid": 25, "dur": 0},{"ph": "X", "name": "11", "ts": 8904478, "pid": 25, "dur": 0},{"ph": "X", "name": "10", "ts": 8905587, "pid": 25, "dur": 0},{"ph": "X", "name": "12", "ts": 8906697, "pid": 25, "dur": 0},{"ph": "X", "name": "13", "ts": 8906700, "pid": 25, "dur": 0},{"ph": "X", "name": "14", "ts": 8906703, "pid": 25, "dur": 0},{"ph": "X", "name": "23", "ts": 8916301, "pid": 25, "dur": 0},{"ph": "X", "name": "2", "ts": 8920545, "pid": 25, "dur": 0},{"ph": "X", "name": "1", "ts": 8921598, "pid": 25, "dur": 0},{"ph": "X", "name": "29", "ts": 8922672, "pid": 25, "dur": 0},{"ph": "X", "name": "31", "ts": 8922676, "pid": 25, "dur": 0},{"ph": "X", "name": "0", "ts": 8923705, "pid": 25, "dur": 0},{"ph": "X", "name": "21", "ts": 8923734, "pid": 25, "dur": 0},{"ph": "X", "name": "22", "ts": 8923737, "pid": 25, "dur": 0},{"ph": "X", "name": "3", "ts": 8924781, "pid": 25, "dur": 0},{"ph": "X", "name": "20", "ts": 8924792, "pid": 25, "dur": 0},{"ph": "X", "name": "19", "ts": 8925871, "pid": 25, "dur": 0},{"ph": "X", "name": "28", "ts": 8925882, "pid": 25, "dur": 0},{"ph": "X", "name": "16", "ts": 8926908, "pid": 25, "dur": 0},{"ph": "X", "name": "17", "ts": 8926910, "pid": 25, "dur": 0},{"ph": "X", "name": "18", "ts": 8926914, "pid": 25, "dur": 0},{"ph": "X", "name": "24", "ts": 8927972, "pid": 25, "dur": 0},{"ph": "X", "name": "25", "ts": 8927975, "pid": 25, "dur": 0},{"ph": "X", "name": "26", "ts": 8927977, "pid": 25, "dur": 0},{"ph": "X", "name": "27", "ts": 8927980, "pid": 25, "dur": 0},{"ph": "X", "name": "30", "ts": 8950309, "pid": 25, "dur": 0},{"ph": "E", "ts": 8950311, "pid": 25},{"ph": "B", "name": "ALLREDUCE", "ts": 8950358, "pid": 25},{"ph": "B", "name": "WAIT_FOR_DATA", "ts": 8950361, "pid": 25},{"ph": "E", "ts": 8950369, "pid": 25},{"ph": "B", "name": "WAIT_FOR_OTHER_TENSOR_DATA", "ts": 8950374, "pid": 25},{"ph": "E", "ts": 8950432, "pid": 25},{"ph": "B", "name": "QUEUE", "ts": 8950561, "pid": 25},{"ph": "E", "ts": 8950572, "pid": 25},{"ph": "B", "name": "NCCL_ALLREDUCE", "ts": 8950576, "pid": 25},{"ph": "E", "ts": 8974140, "pid": 25},{"ph": "E", "ts": 8974166, "pid": 25, "args": {"dtype": "float32", "shape": "[16777216]"}},{"name": "process_name", "ph": "M", "pid": 26, "args": {"name": "allreduce.noname.26"}},
{"name": "process_sort_index", "ph": "M", "pid": 26, "args": {"sort_index": 26}},
{"ph": "B", "name": "NEGOTIATE_ALLREDUCE", "ts": 9341521, "pid": 26},{"ph": "X", "name": "7", "ts": 9341523, "pid": 26, "dur": 0},{"ph": "X", "name": "14", "ts": 9342558, "pid": 26, "dur": 0},{"ph": "X", "name": "6", "ts": 9347838, "pid": 26, "dur": 0},{"ph": "X", "name": "4", "ts": 9351014, "pid": 26, "dur": 0},{"ph": "X", "name": "15", "ts": 9352082, "pid": 26, "dur": 0},{"ph": "X", "name": "5", "ts": 9353133, "pid": 26, "dur": 0},{"ph": "X", "name": "9", "ts": 9359500, "pid": 26, "dur": 0},{"ph": "X", "name": "10", "ts": 9362747, "pid": 26, "dur": 0},{"ph": "X", "name": "11", "ts": 9362750, "pid": 26, "dur": 0},{"ph": "X", "name": "12", "ts": 9366951, "pid": 26, "dur": 0},{"ph": "X", "name": "13", "ts": 9366954, "pid": 26, "dur": 0},{"ph": "X", "name": "30", "ts": 9366966, "pid": 26, "dur": 0},{"ph": "X", "name": "2", "ts": 9382834, "pid": 26, "dur": 0},{"ph": "X", "name": "3", "ts": 9384954, "pid": 26, "dur": 0},{"ph": "X", "name": "8", "ts": 9388153, "pid": 26, "dur": 0},{"ph": "X", "name": "23", "ts": 9391359, "pid": 26, "dur": 0},{"ph": "X", "name": "1", "ts": 9393461, "pid": 26, "dur": 0},{"ph": "X", "name": "29", "ts": 9396662, "pid": 26, "dur": 0},{"ph": "X", "name": "0", "ts": 9397687, "pid": 26, "dur": 0},{"ph": "X", "name": "31", "ts": 9397720, "pid": 26, "dur": 0},{"ph": "X", "name": "16", "ts": 9398779, "pid": 26, "dur": 0},{"ph": "X", "name": "21", "ts": 9399837, "pid": 26, "dur": 0},{"ph": "X", "name": "17", "ts": 9400896, "pid": 26, "dur": 0},{"ph": "X", "name": "18", "ts": 9400899, "pid": 26, "dur": 0},{"ph": "X", "name": "20", "ts": 9401961, "pid": 26, "dur": 0},{"ph": "X", "name": "22", "ts": 9401964, "pid": 26, "dur": 0},{"ph": "X", "name": "24", "ts": 9405146, "pid": 26, "dur": 0},{"ph": "X", "name": "25", "ts": 9406208, "pid": 26, "dur": 0},{"ph": "X", "name": "26", "ts": 9406212, "pid": 26, "dur": 0},{"ph": "X", "name": "27", "ts": 9406222, "pid": 26, "dur": 0},{"ph": "X", "name": "28", "ts": 9406225, "pid": 26, "dur": 0},{"ph": "X", "name": "19", "ts": 9442369, "pid": 26, "dur": 0},{"ph": "E", "ts": 9442372, "pid": 26},{"ph": "B", "name": "ALLREDUCE", "ts": 9442428, "pid": 26},{"ph": "B", "name": "WAIT_FOR_DATA", "ts": 9442431, "pid": 26},{"ph": "E", "ts": 9442440, "pid": 26},{"ph": "B", "name": "WAIT_FOR_OTHER_TENSOR_DATA", "ts": 9442442, "pid": 26},{"ph": "E", "ts": 9442499, "pid": 26},{"ph": "B", "name": "QUEUE", "ts": 9442626, "pid": 26},{"ph": "E", "ts": 9442638, "pid": 26},{"ph": "B", "name": "NCCL_ALLREDUCE", "ts": 9442642, "pid": 26},{"ph": "E", "ts": 9489776, "pid": 26},{"ph": "E", "ts": 9489801, "pid": 26, "args": {"dtype": "float32", "shape": "[33554432]"}},{"name": "process_name", "ph": "M", "pid": 27, "args": {"name": "allreduce.noname.27"}},
{"name": "process_sort_index", "ph": "M", "pid": 27, "args": {"sort_index": 27}},
{"ph": "B", "name": "NEGOTIATE_ALLREDUCE", "ts": 10218553, "pid": 27},{"ph": "X", "name": "7", "ts": 10218555, "pid": 27, "dur": 0},{"ph": "X", "name": "14", "ts": 10221723, "pid": 27, "dur": 0},{"ph": "X", "name": "6", "ts": 10232335, "pid": 27, "dur": 0},{"ph": "X", "name": "4", "ts": 10238708, "pid": 27, "dur": 0},{"ph": "X", "name": "15", "ts": 10241902, "pid": 27, "dur": 0},{"ph": "X", "name": "5", "ts": 10245082, "pid": 27, "dur": 0},{"ph": "X", "name": "9", "ts": 10253594, "pid": 27, "dur": 0},{"ph": "X", "name": "10", "ts": 10256776, "pid": 27, "dur": 0},{"ph": "X", "name": "11", "ts": 10256779, "pid": 27, "dur": 0},{"ph": "X", "name": "8", "ts": 10257833, "pid": 27, "dur": 0},{"ph": "X", "name": "12", "ts": 10266350, "pid": 27, "dur": 0},{"ph": "X", "name": "13", "ts": 10266353, "pid": 27, "dur": 0},{"ph": "X", "name": "30", "ts": 10274904, "pid": 27, "dur": 0},{"ph": "X", "name": "19", "ts": 10285527, "pid": 27, "dur": 0},{"ph": "X", "name": "2", "ts": 10311038, "pid": 27, "dur": 0},{"ph": "X", "name": "3", "ts": 10312093, "pid": 27, "dur": 0},{"ph": "X", "name": "23", "ts": 10321693, "pid": 27, "dur": 0},{"ph": "X", "name": "29", "ts": 10331269, "pid": 27, "dur": 0},{"ph": "X", "name": "31", "ts": 10332319, "pid": 27, "dur": 0},{"ph": "X", "name": "0", "ts": 10333346, "pid": 27, "dur": 0},{"ph": "X", "name": "16", "ts": 10334427, "pid": 27, "dur": 0},{"ph": "X", "name": "21", "ts": 10338681, "pid": 27, "dur": 0},{"ph": "X", "name": "20", "ts": 10342932, "pid": 27, "dur": 0},{"ph": "X", "name": "22", "ts": 10342936, "pid": 27, "dur": 0},{"ph": "X", "name": "24", "ts": 10346117, "pid": 27, "dur": 0},{"ph": "X", "name": "26", "ts": 10347179, "pid": 27, "dur": 0},{"ph": "X", "name": "25", "ts": 10348236, "pid": 27, "dur": 0},{"ph": "X", "name": "27", "ts": 10348240, "pid": 27, "dur": 0},{"ph": "X", "name": "17", "ts": 10349292, "pid": 27, "dur": 0},{"ph": "X", "name": "1", "ts": 10352748, "pid": 27, "dur": 0},{"ph": "X", "name": "28", "ts": 10352765, "pid": 27, "dur": 0},{"ph": "X", "name": "18", "ts": 10376083, "pid": 27, "dur": 0},{"ph": "E", "ts": 10376087, "pid": 27},{"ph": "B", "name": "ALLREDUCE", "ts": 10376205, "pid": 27},{"ph": "B", "name": "WAIT_FOR_DATA", "ts": 10376210, "pid": 27},{"ph": "E", "ts": 10376226, "pid": 27},{"ph": "B", "name": "WAIT_FOR_OTHER_TENSOR_DATA", "ts": 10376230, "pid": 27},{"ph": "E", "ts": 10376296, "pid": 27},{"ph": "B", "name": "QUEUE", "ts": 10376507, "pid": 27},{"ph": "E", "ts": 10376526, "pid": 27},{"ph": "B", "name": "NCCL_ALLREDUCE", "ts": 10376533, "pid": 27},{"ph": "E", "ts": 10470849, "pid": 27},{"ph": "E", "ts": 10470876, "pid": 27, "args": {"dtype": "float32", "shape": "[67108864]"}},{"name": "process_name", "ph": "M", "pid": 28, "args": {"name": "allreduce.noname.28"}},
{"name": "process_sort_index", "ph": "M", "pid": 28, "args": {"sort_index": 28}},
{"ph": "B", "name": "NEGOTIATE_ALLREDUCE", "ts": 11973601, "pid": 28},{"ph": "X", "name": "9", "ts": 11973606, "pid": 28, "dur": 0},{"ph": "X", "name": "11", "ts": 11974465, "pid": 28, "dur": 0},{"ph": "X", "name": "10", "ts": 11976580, "pid": 28, "dur": 0},{"ph": "X", "name": "7", "ts": 11984028, "pid": 28, "dur": 0},{"ph": "X", "name": "6", "ts": 11991540, "pid": 28, "dur": 0},{"ph": "X", "name": "15", "ts": 11998913, "pid": 28, "dur": 0},{"ph": "X", "name": "4", "ts": 12007405, "pid": 28, "dur": 0},{"ph": "X", "name": "14", "ts": 12007416, "pid": 28, "dur": 0},{"ph": "X", "name": "8", "ts": 12009549, "pid": 28, "dur": 0},{"ph": "X", "name": "13", "ts": 12012715, "pid": 28, "dur": 0},{"ph": "X", "name": "12", "ts": 12014842, "pid": 28, "dur": 0},{"ph": "X", "name": "30", "ts": 12053125, "pid": 28, "dur": 0},{"ph": "X", "name": "5", "ts": 12063735, "pid": 28, "dur": 0},{"ph": "X", "name": "19", "ts": 12084544, "pid": 28, "dur": 0},{"ph": "X", "name": "27", "ts": 12084656, "pid": 28, "dur": 0},{"ph": "X", "name": "31", "ts": 12156032, "pid": 28, "dur": 0},{"ph": "X", "name": "29", "ts": 12157045, "pid": 28, "dur": 0},{"ph": "X", "name": "23", "ts": 12159151, "pid": 28, "dur": 0},{"ph": "X", "name": "18", "ts": 12166579, "pid": 28, "dur": 0},{"ph": "X", "name": "2", "ts": 12176009, "pid": 28, "dur": 0},{"ph": "X", "name": "3", "ts": 12176013, "pid": 28, "dur": 0},{"ph": "X", "name": "16", "ts": 12176027, "pid": 28, "dur": 0},{"ph": "X", "name": "17", "ts": 12176030, "pid": 28, "dur": 0},{"ph": "X", "name": "21", "ts": 12176152, "pid": 28, "dur": 0},{"ph": "X", "name": "20", "ts": 12178292, "pid": 28, "dur": 0},{"ph": "X", "name": "22", "ts": 12178297, "pid": 28, "dur": 0},{"ph": "X", "name": "25", "ts": 12179356, "pid": 28, "dur": 0},{"ph": "X", "name": "26", "ts": 12179360, "pid": 28, "dur": 0},{"ph": "X", "name": "24", "ts": 12181477, "pid": 28, "dur": 0},{"ph": "X", "name": "28", "ts": 12195312, "pid": 28, "dur": 0},{"ph": "X", "name": "0", "ts": 12240989, "pid": 28, "dur": 0},{"ph": "X", "name": "1", "ts": 12324096, "pid": 28, "dur": 0},{"ph": "E", "ts": 12324099, "pid": 28},{"ph": "B", "name": "ALLREDUCE", "ts": 12324201, "pid": 28},{"ph": "B", "name": "WAIT_FOR_DATA", "ts": 12324204, "pid": 28},{"ph": "E", "ts": 12324216, "pid": 28},{"ph": "B", "name": "WAIT_FOR_OTHER_TENSOR_DATA", "ts": 12324219, "pid": 28},{"ph": "E", "ts": 12324277, "pid": 28},{"ph": "B", "name": "QUEUE", "ts": 12324541, "pid": 28},{"ph": "E", "ts": 12324578, "pid": 28},{"ph": "B", "name": "NCCL_ALLREDUCE", "ts": 12324591, "pid": 28},{"ph": "E", "ts": 12513297, "pid": 28},{"ph": "E", "ts": 12513324, "pid": 28, "args": {"dtype": "float32", "shape": "[134217728]"}},{"name": "process_name", "ph": "M", "pid": 29, "args": {"name": "allreduce.noname.29"}},
{"name": "process_sort_index", "ph": "M", "pid": 29, "args": {"sort_index": 29}},
{"ph": "B", "name": "NEGOTIATE_ALLREDUCE", "ts": 15483369, "pid": 29},{"ph": "X", "name": "14", "ts": 15483371, "pid": 29, "dur": 0},{"ph": "X", "name": "10", "ts": 15486669, "pid": 29, "dur": 0},{"ph": "X", "name": "11", "ts": 15486672, "pid": 29, "dur": 0},{"ph": "X", "name": "7", "ts": 15487754, "pid": 29, "dur": 0},{"ph": "X", "name": "9", "ts": 15487758, "pid": 29, "dur": 0},{"ph": "X", "name": "6", "ts": 15536585, "pid": 29, "dur": 0},{"ph": "X", "name": "4", "ts": 15572754, "pid": 29, "dur": 0},{"ph": "X", "name": "8", "ts": 15584445, "pid": 29, "dur": 0},{"ph": "X", "name": "12", "ts": 15599345, "pid": 29, "dur": 0},{"ph": "X", "name": "13", "ts": 15600399, "pid": 29, "dur": 0},{"ph": "X", "name": "15", "ts": 15600404, "pid": 29, "dur": 0},{"ph": "X", "name": "5", "ts": 15663251, "pid": 29, "dur": 0},{"ph": "X", "name": "30", "ts": 15667529, "pid": 29, "dur": 0},{"ph": "X", "name": "19", "ts": 15698414, "pid": 29, "dur": 0},{"ph": "X", "name": "2", "ts": 15826863, "pid": 29, "dur": 0},{"ph": "X", "name": "3", "ts": 15830019, "pid": 29, "dur": 0},{"ph": "X", "name": "31", "ts": 15863085, "pid": 29, "dur": 0},{"ph": "X", "name": "18", "ts": 15907838, "pid": 29, "dur": 0},{"ph": "X", "name": "16", "ts": 15914233, "pid": 29, "dur": 0},{"ph": "X", "name": "17", "ts": 15914235, "pid": 29, "dur": 0},{"ph": "X", "name": "25", "ts": 15914243, "pid": 29, "dur": 0},{"ph": "X", "name": "29", "ts": 15923839, "pid": 29, "dur": 0},{"ph": "X", "name": "20", "ts": 15924920, "pid": 29, "dur": 0},{"ph": "X", "name": "21", "ts": 15924923, "pid": 29, "dur": 0},{"ph": "X", "name": "23", "ts": 15927042, "pid": 29, "dur": 0},{"ph": "X", "name": "0", "ts": 15928056, "pid": 29, "dur": 0},{"ph": "X", "name": "24", "ts": 15947281, "pid": 29, "dur": 0},{"ph": "X", "name": "22", "ts": 15968717, "pid": 29, "dur": 0},{"ph": "X", "name": "28", "ts": 16069857, "pid": 29, "dur": 0},{"ph": "X", "name": "27", "ts": 16098828, "pid": 29, "dur": 0},{"ph": "X", "name": "26", "ts": 16390083, "pid": 29, "dur": 0},{"ph": "X", "name": "1", "ts": 16996590, "pid": 29, "dur": 0},{"ph": "E", "ts": 16996596, "pid": 29},{"ph": "B", "name": "ALLREDUCE", "ts": 16996678, "pid": 29},{"ph": "B", "name": "WAIT_FOR_DATA", "ts": 16996680, "pid": 29},{"ph": "E", "ts": 16996711, "pid": 29},{"ph": "B", "name": "WAIT_FOR_OTHER_TENSOR_DATA", "ts": 16996713, "pid": 29},{"ph": "E", "ts": 16996770, "pid": 29},{"ph": "B", "name": "QUEUE", "ts": 16996925, "pid": 29},{"ph": "E", "ts": 16996948, "pid": 29},{"ph": "B", "name": "NCCL_ALLREDUCE", "ts": 16996956, "pid": 29},{"ph": "E", "ts": 17374714, "pid": 29},{"ph": "E", "ts": 17374745, "pid": 29, "args": {"dtype": "float32", "shape": "[268435456]"}}]